{
  "id": "vol1-ch01-sec05",
  "title": "Trigonometric Functions and Their Properties",
  "chapter": 1,
  "section": 5,
  "book": "vol1",
  "objectives": [
    "Define sine, cosine, and the four remaining trigonometric functions using the unit circle",
    "Evaluate trigonometric functions at standard angles using reference triangles and quadrant signs",
    "Apply key trigonometric identities including Pythagorean, double-angle, and sum/difference formulas",
    "Model periodic phenomena using sinusoidal functions with appropriate amplitude, period, and phase shift"
  ],
  "devotional": {
    "title": "The God Who Names the Stars",
    "scripture": "Psalm 147:4",
    "content": "\"He determines the number of the stars and calls them each by name.\" The same God who set the celestial bodies in their orbits\u2014cycles so precise we can predict eclipses millennia in advance\u2014gave us the mathematics to describe that motion. Trigonometric functions capture the essence of repetition: the rising and setting of the sun, the phases of the moon, the rhythm of the tides. In studying these functions, we trace the fingerprints of a Creator whose faithfulness is as constant as the cosine wave itself."
  },
  "content": [
    {
      "type": "paragraph",
      "text": "A child on a Ferris wheel rises, crests, descends, and rises again. Ocean tides swell and recede with the moon. A guitar string vibrates back and forth hundreds of times each second. These phenomena share a common thread: they *repeat*. The mathematics of repetition is the mathematics of trigonometric functions, and you have been studying them since your first encounter with right triangles."
    },
    {
      "type": "paragraph",
      "text": "This section is a *review*. You should already know the definitions of sine, cosine, and tangent; you should be comfortable evaluating them at standard angles and sketching their graphs. Our purpose here is not to teach these ideas from scratch but to *sharpen the tools* we will need throughout calculus. When we differentiate $\\sin x$ in Chapter 4, when we integrate $\\sec^{2} x$ in Chapter 6, when we tackle trigonometric substitution in Chapter 8\u2014we will need these facts at our fingertips, not buried under dust."
    },
    {
      "type": "figure",
      "id": "fig-1.5-unit-circle",
      "src": "/figures/vol1/ch01/sec05-unit-circle.svg",
      "caption": "The unit circle. The coordinates of the terminal point~$P$ give $\\cos t$ and $\\sin t$.",
      "alt": "Figure: Unit Circle"
    },
    {
      "type": "paragraph",
      "text": "Let us begin where all of trigonometry begins: the unit circle."
    },
    {
      "type": "heading",
      "level": 2,
      "text": "The Unit Circle"
    },
    {
      "type": "paragraph",
      "text": "The unit circle is the circle of radius 1 centered at the origin in the $xy$-plane. Every point on this circle can be reached by starting at $(1,0)$ and traveling a signed arc length $t$: counterclockwise when $t > 0$, clockwise when $t < 0$. The terminal point of that arc is the key to everything."
    },
    {
      "type": "definition",
      "id": "def-1.9",
      "number": "1.9",
      "title": "Sine and Cosine",
      "content": "Let $t$ be a real number, and let $P(x,y)$ be the point on the unit circle reached by traveling an arc of length $|t|$ from $(1,0)$, counterclockwise if $t > 0$ and clockwise if $t < 0$. Then\n\n$$\\cos t = x, \\qquad \\sin t = y.$$\n\nThe **cosine** of $t$ is the $x$-coordinate, and the **sine** of $t$ is the $y$-coordinate, of the terminal point $P$."
    },
    {
      "type": "paragraph",
      "text": "Because $P$ lies on the circle $x^{2}+y^{2}=1$, we obtain the most fundamental identity in all of trigonometry for free:"
    },
    {
      "type": "paragraph",
      "text": "$$\\cos^{2} t + \\sin^{2} t = 1 \\quad \\text{for every real number } t.$$"
    },
    {
      "type": "paragraph",
      "text": "The remaining four trigonometric functions are defined in terms of sine and cosine:"
    },
    {
      "type": "definition",
      "id": "def-1.10",
      "number": "1.10",
      "title": "The Four Remaining Trigonometric Functions",
      "content": "$$\\tan t = \\frac{\\sin t}{\\cos t}, \\qquad \\cot t = \\frac{\\cos t}{\\sin t}, \\qquad \\sec t = \\frac{1}{\\cos t}, \\qquad \\csc t = \\frac{1}{\\sin t},$$\n\neach defined wherever its denominator is nonzero."
    },
    {
      "type": "heading",
      "level": 2,
      "text": "Key Values: The Reference Triangles"
    },
    {
      "type": "paragraph",
      "text": "Two special right triangles\u2014the **45\u201345\u201390** and the **30\u201360\u201390**\u2014produce every \"nice\" value of sine and cosine that you are expected to know. When these triangles are inscribed in the unit circle, the hypotenuse has length 1, and the legs give the coordinates of the terminal point."
    },
    {
      "type": "figure",
      "id": "fig-1.5-reference-triangles",
      "src": "/figures/vol1/ch01/sec05-reference-triangles.svg",
      "caption": "The two reference triangles inscribed in the unit circle.",
      "alt": "Figure: Reference Triangles"
    },
    {
      "type": "paragraph",
      "text": "The table below collects the values you should know cold. Do not memorize it mechanically\u2014learn the two reference triangles, and you can reconstruct every entry."
    },
    {
      "type": "table",
      "id": "tab-trig-values",
      "caption": "Trigonometric values at the first-quadrant standard angles.",
      "headers": [
        "$t$",
        "$0$",
        "$\\frac{\\pi}{6}$",
        "$\\frac{\\pi}{4}$",
        "$\\frac{\\pi}{3}$",
        "$\\frac{\\pi}{2}$"
      ],
      "rows": [
        [
          "$\\cos t$",
          "$1$",
          "$\\frac{\\sqrt{3}}{2}$",
          "$\\frac{\\sqrt{2}}{2}$",
          "$\\frac{1}{2}$",
          "$0$"
        ],
        [
          "$\\sin t$",
          "$0$",
          "$\\frac{1}{2}$",
          "$\\frac{\\sqrt{2}}{2}$",
          "$\\frac{\\sqrt{3}}{2}$",
          "$1$"
        ],
        [
          "$\\tan t$",
          "$0$",
          "$\\frac{\\sqrt{3}}{3}$",
          "$1$",
          "$\\sqrt{3}$",
          "undef."
        ]
      ]
    },
    {
      "type": "strategy",
      "id": "strategy-1.1",
      "title": "Evaluating Trig at Any Standard Angle",
      "content": "To find $\\sin t$ or $\\cos t$ at any standard angle:\n\n1. **Find the reference angle.** The reference angle $\\bar{t}$ is the acute angle between the terminal side and the $x$-axis.\n\n2. **Evaluate at the reference angle.** Use the table above (or the reference triangle) to find $\\sin\\bar{t}$ and $\\cos\\bar{t}$.\n\n3. **Attach the correct sign.** Determine which quadrant the terminal side lies in, and apply the appropriate sign (All Students Take Calculus: all positive in QI, sine in QII, tangent in QIII, cosine in QIV)."
    },
    {
      "type": "example",
      "id": "ex-1.17",
      "number": "1.17",
      "title": "Evaluating at a Non-First-Quadrant Angle",
      "problem": "Evaluate $\\sin\\left(\\frac{5\\pi}{6}\\right)$ and $\\cos\\left(\\frac{5\\pi}{6}\\right)$.",
      "solution": "The angle $\\frac{5\\pi}{6}$ lies in the second quadrant. Its reference angle is\n\n$$\\bar{t} = \\pi - \\frac{5\\pi}{6} = \\frac{\\pi}{6}.$$\n\nFrom the table, $\\sin\\frac{\\pi}{6} = \\frac{1}{2}$ and $\\cos\\frac{\\pi}{6} = \\frac{\\sqrt{3}}{2}$. In the second quadrant, sine is positive and cosine is negative, so\n\n$$\\sin\\frac{5\\pi}{6} = \\frac{1}{2}, \\qquad \\cos\\frac{5\\pi}{6} = -\\frac{\\sqrt{3}}{2}.$$"
    },
    {
      "type": "example",
      "id": "ex-1.18",
      "number": "1.18",
      "title": "A Third-Quadrant Angle",
      "problem": "Evaluate $\\tan\\left(\\frac{4\\pi}{3}\\right)$.",
      "solution": "The angle $\\frac{4\\pi}{3}$ lies in the third quadrant. The reference angle is\n\n$$\\bar{t} = \\frac{4\\pi}{3} - \\pi = \\frac{\\pi}{3}.$$\n\nWe know $\\tan\\frac{\\pi}{3} = \\sqrt{3}$. In the third quadrant, tangent is positive (both sine and cosine are negative, so their ratio is positive). Therefore,\n\n$$\\tan\\frac{4\\pi}{3} = \\sqrt{3}.$$"
    },
    {
      "type": "heading",
      "level": 2,
      "text": "Graphs of the Trigonometric Functions"
    },
    {
      "type": "paragraph",
      "text": "The graphs of $\\sin x$ and $\\cos x$ are the fundamental waveforms of mathematics. Both are continuous, smooth, and periodic with period $2\\pi$."
    },
    {
      "type": "definition",
      "id": "def-1.11",
      "number": "1.11",
      "title": "Period and Amplitude",
      "content": "A function $f$ is **periodic** with **period** $T > 0$ if\n\n$$f(x + T) = f(x) \\quad \\text{for all } x \\text{ in the domain of } f,$$\n\nand $T$ is the smallest such positive number. For a sinusoidal function $f(x) = A\\sin(Bx + C) + D$ or $f(x) = A\\cos(Bx + C) + D$, the **amplitude** is $|A|$, the period is $\\frac{2\\pi}{|B|}$, the **phase shift** is $-\\frac{C}{B}$, and the **vertical shift** is $D$."
    },
    {
      "type": "paragraph",
      "text": "Key features to remember:"
    },
    {
      "type": "list",
      "ordered": false,
      "items": [
        "**Sine:** $\\sin 0 = 0$; rises to $1$ at $\\frac{\\pi}{2}$; returns to $0$ at $\\pi$; dips to $-1$ at $\\frac{3\\pi}{2}$; completes the cycle at $2\\pi$. Domain: $(-\\infty,\\infty)$. Range: $[-1,1]$.",
        "**Cosine:** $\\cos 0 = 1$; falls to $0$ at $\\frac{\\pi}{2}$; reaches $-1$ at $\\pi$; returns to $0$ at $\\frac{3\\pi}{2}$; completes the cycle at $2\\pi$. Domain: $(-\\infty,\\infty)$. Range: $[-1,1]$.",
        "**Symmetry:** $\\sin x$ is an *odd* function ($\\sin(-x) = -\\sin x$), and $\\cos x$ is an *even* function ($\\cos(-x) = \\cos x$)."
      ]
    },
    {
      "type": "example",
      "id": "ex-1.19",
      "number": "1.19",
      "title": "Reading a Transformed Sinusoid",
      "problem": "Identify the amplitude, period, phase shift, and vertical shift of\n\n$$f(x) = 3\\sin\\left(2x - \\frac{\\pi}{3}\\right) + 1.$$",
      "solution": "We compare with the general form $A\\sin(Bx + C) + D$. Here $A = 3$, $B = 2$, $C = -\\frac{\\pi}{3}$, and $D = 1$. Therefore:\n\n- Amplitude $= |A| = 3$.\n- Period $= \\frac{2\\pi}{|B|} = \\frac{2\\pi}{2} = \\pi$.\n- Phase shift $= -\\frac{C}{B} = -\\frac{-\\pi/3}{2} = \\frac{\\pi}{6}$ (shifted $\\frac{\\pi}{6}$ to the right).\n- Vertical shift $= D = 1$ (shifted $1$ unit up).\n\nThe graph oscillates between $1 - 3 = -2$ and $1 + 3 = 4$, completing one full cycle every $\\pi$ units."
    },
    {
      "type": "heading",
      "level": 2,
      "text": "The Tangent Function and Its Relatives"
    },
    {
      "type": "paragraph",
      "text": "The graph of $y = \\tan x$ looks quite different from the gentle waves of sine and cosine. Because $\\tan x = \\frac{\\sin x}{\\cos x}$, vertical asymptotes occur wherever $\\cos x = 0$\u2014that is, at $x = \\pm\\frac{\\pi}{2}, \\pm\\frac{3\\pi}{2}, \\ldots$ Between consecutive asymptotes the function increases from $-\\infty$ to $+\\infty$, giving tangent a period of $\\pi$ (not $2\\pi$)."
    },
    {
      "type": "paragraph",
      "text": "The reciprocal functions\u2014$\\csc x = 1/\\sin x$, $\\sec x = 1/\\cos x$, and $\\cot x = \\cos x / \\sin x$\u2014arise less often in elementary calculus but will appear when we study certain integrals and derivatives. Their graphs inherit asymptotes from the zeros of sine and cosine, respectively."
    },
    {
      "type": "caution",
      "title": "Tangent is Not Bounded",
      "content": "Unlike sine and cosine, the tangent function has no finite maximum or minimum. Its range is $(-\\infty,\\infty)$. Do not assume that all trigonometric functions are bounded\u2014this is a common source of errors in limit problems."
    },
    {
      "type": "heading",
      "level": 2,
      "text": "Key Identities: A Reference"
    },
    {
      "type": "paragraph",
      "text": "The trigonometric identities below are tools, not theorems to be proved from scratch every time you need them. You proved them in precalculus; now you should *know* them. We collect them here for reference, organized by type."
    },
    {
      "type": "heading",
      "level": 3,
      "text": "Pythagorean Identities"
    },
    {
      "type": "paragraph",
      "text": "$$\\sin^{2} t + \\cos^{2} t = 1$$\n\n$$1 + \\tan^{2} t = \\sec^{2} t$$\n\n$$1 + \\cot^{2} t = \\csc^{2} t$$\n\n(The second and third follow by dividing the first by $\\cos^{2} t$ and $\\sin^{2} t$, respectively.)"
    },
    {
      "type": "heading",
      "level": 3,
      "text": "Sum and Difference Formulas"
    },
    {
      "type": "paragraph",
      "text": "$$\\sin(\\alpha \\pm \\beta) = \\sin\\alpha\\cos\\beta \\pm \\cos\\alpha\\sin\\beta$$\n\n$$\\cos(\\alpha \\pm \\beta) = \\cos\\alpha\\cos\\beta \\mp \\sin\\alpha\\sin\\beta$$\n\n$$\\tan(\\alpha \\pm \\beta) = \\frac{\\tan\\alpha \\pm \\tan\\beta}{1 \\mp \\tan\\alpha\\tan\\beta}$$"
    },
    {
      "type": "heading",
      "level": 3,
      "text": "Double-Angle Formulas"
    },
    {
      "type": "paragraph",
      "text": "$$\\sin 2\\theta = 2\\sin\\theta\\cos\\theta$$\n\n$$\\cos 2\\theta = \\cos^{2}\\theta - \\sin^{2}\\theta = 2\\cos^{2}\\theta - 1 = 1 - 2\\sin^{2}\\theta$$"
    },
    {
      "type": "heading",
      "level": 3,
      "text": "Half-Angle (Power-Reduction) Formulas"
    },
    {
      "type": "paragraph",
      "text": "$$\\sin^{2}\\theta = \\frac{1 - \\cos 2\\theta}{2}$$\n\n$$\\cos^{2}\\theta = \\frac{1 + \\cos 2\\theta}{2}$$\n\nThese will be indispensable in Chapter 8 when we integrate even powers of sine and cosine."
    },
    {
      "type": "example",
      "id": "ex-1.20",
      "number": "1.20",
      "title": "Using Identities to Simplify",
      "problem": "Simplify the expression $\\frac{\\sin 2x}{1 + \\cos 2x}$.",
      "solution": "We apply the double-angle formulas. The numerator is $\\sin 2x = 2\\sin x\\cos x$. For the denominator, we use the form $\\cos 2x = 2\\cos^{2} x - 1$, so\n\n$$1 + \\cos 2x = 1 + (2\\cos^{2} x - 1) = 2\\cos^{2} x.$$\n\nTherefore,\n\n$$\\frac{\\sin 2x}{1 + \\cos 2x} = \\frac{2\\sin x\\cos x}{2\\cos^{2} x} = \\frac{\\sin x}{\\cos x} = \\tan x,$$\n\nprovided $\\cos x \\neq 0$."
    },
    {
      "type": "example",
      "id": "ex-1.21",
      "number": "1.21",
      "title": "Verifying an Identity",
      "problem": "Verify that $\\sec^{2}\\theta - 1 = \\tan^{2}\\theta$.",
      "solution": "Starting from the left side and applying the Pythagorean identity $1 + \\tan^{2} t = \\sec^{2} t$ rearranged:\n\n$$\\sec^{2}\\theta - 1 = (1 + \\tan^{2}\\theta) - 1 = \\tan^{2}\\theta.$$\n\nThe two sides are equal for all $\\theta$ where both are defined."
    },
    {
      "type": "heading",
      "level": 2,
      "text": "Inverse Trigonometric Functions: A Preview"
    },
    {
      "type": "paragraph",
      "text": "None of the six trigonometric functions is one-to-one on its natural domain\u2014each repeats its values infinitely often. To define an inverse, we must *restrict* the domain to an interval on which the function is one-to-one."
    },
    {
      "type": "definition",
      "id": "def-1.12",
      "number": "1.12",
      "title": "Principal Inverse Trigonometric Functions",
      "content": "1. $y = \\sin^{-1} x$ (or $\\arcsin x$) is defined for $x \\in [-1,1]$ with range $\\left[-\\frac{\\pi}{2}, \\frac{\\pi}{2}\\right]$. It returns the unique angle in this interval whose sine is $x$.\n\n2. $y = \\cos^{-1} x$ (or $\\arccos x$) is defined for $x \\in [-1,1]$ with range $[0,\\pi]$. It returns the unique angle in this interval whose cosine is $x$.\n\n3. $y = \\tan^{-1} x$ (or $\\arctan x$) is defined for $x \\in (-\\infty,\\infty)$ with range $\\left(-\\frac{\\pi}{2}, \\frac{\\pi}{2}\\right)$. It returns the unique angle in this interval whose tangent is $x$."
    },
    {
      "type": "caution",
      "title": "$\\sin^{-1} x$ Does Not Mean $(\\sin x)^{-1}$",
      "content": "The notation $\\sin^{-1} x$ denotes the *inverse function* of sine, not the reciprocal. We write $(\\sin x)^{-1} = \\csc x$ for the reciprocal. This is an unfortunate but standard ambiguity. When in doubt, use the notation $\\arcsin x$."
    },
    {
      "type": "example",
      "id": "ex-1.22",
      "number": "1.22",
      "title": "Evaluating Inverse Trig Functions",
      "problem": "Evaluate: (a) $\\sin^{-1}\\left(\\frac{\\sqrt{3}}{2}\\right)$, (b) $\\tan^{-1}(-1)$.",
      "solution": "(a) We need an angle $\\theta \\in [-\\frac{\\pi}{2}, \\frac{\\pi}{2}]$ with $\\sin\\theta = \\frac{\\sqrt{3}}{2}$. From our table, $\\theta = \\frac{\\pi}{3}$.\n\n(b) We need $\\theta \\in (-\\frac{\\pi}{2}, \\frac{\\pi}{2})$ with $\\tan\\theta = -1$. Since $\\tan(-\\frac{\\pi}{4}) = -1$, we have $\\theta = -\\frac{\\pi}{4}$."
    },
    {
      "type": "paragraph",
      "text": "We will return to the inverse trigonometric functions in Chapter 7, where we study their derivatives and the elegant integrals they produce. For now, it is enough to know what they mean and how to evaluate them at standard values."
    },
    {
      "type": "heading",
      "level": 2,
      "text": "Trigonometric Functions in the World"
    },
    {
      "type": "paragraph",
      "text": "Why do trigonometric functions appear so often in nature? Because nature is full of *cycles*. Anything that repeats\u2014tides, seasons, heartbeats, vibrating strings, alternating current, the orbit of a planet\u2014can be modeled by sinusoidal functions."
    },
    {
      "type": "example",
      "id": "ex-1.23",
      "number": "1.23",
      "title": "Modeling Daylight Hours",
      "problem": "In Austin, Texas, the longest day (June 21) has about $14.0$ hours of daylight and the shortest day (December 21) has about $10.1$ hours. Write a sinusoidal model $D(t)$ for the hours of daylight $t$ days after January 1.",
      "solution": "The average daylight is\n\n$$D_{\\text{avg}} = \\frac{14.0 + 10.1}{2} = 12.05 \\text{ hours}.$$\n\nThe amplitude is\n\n$$A = \\frac{14.0 - 10.1}{2} = 1.95 \\text{ hours}.$$\n\nThe period is $365$ days, so $B = \\frac{2\\pi}{365}$. The maximum occurs around day $t = 172$ (June 21). Since cosine reaches its maximum at $0$, we shift:\n\n$$D(t) = 12.05 + 1.95\\cos\\left(\\frac{2\\pi}{365}(t - 172)\\right).$$\n\nThis model predicts $D(172) = 12.05 + 1.95 = 14.0$ hours at the summer solstice and $D(355) \\approx 12.05 - 1.95 = 10.1$ hours at the winter solstice, matching the data."
    },
    {
      "type": "example",
      "id": "ex-1.24",
      "number": "1.24",
      "title": "Simple Harmonic Motion",
      "problem": "A mass on a spring is pulled $6$ cm below its rest position and released. It completes one full oscillation every $0.8$ seconds. Find a function $y(t)$ giving the displacement (in cm) from the rest position at time $t$ seconds.",
      "solution": "Since the mass is released from below the rest position (displacement $= -6$ at $t = 0$), we use\n\n$$y(t) = -A\\cos(Bt).$$\n\nThe amplitude is $A = 6$ and the period is $T = 0.8$, giving $B = \\frac{2\\pi}{0.8} = \\frac{5\\pi}{2}$. Therefore,\n\n$$y(t) = -6\\cos\\left(\\frac{5\\pi}{2}\\,t\\right).$$\n\nWe can verify: $y(0) = -6$ (starting position), $y(0.4) = -6\\cos(\\pi) = 6$ (maximum displacement above rest), and $y(0.8) = -6\\cos(2\\pi) = -6$ (back to starting position)."
    },
    {
      "type": "historical_note",
      "title": "Jean Baptiste Joseph Fourier (1768\u20131830)",
      "content": "Fourier shocked the mathematical world by claiming that *any* periodic function can be written as a sum of sines and cosines. His *Th\u00e9orie analytique de la chaleur* (1822) showed how these \"Fourier series\" solve problems in heat conduction, and the idea revolutionized physics and engineering. Today, Fourier analysis is essential to signal processing, medical imaging, and data compression. Every time you stream music or view a JPEG image, Fourier's insight is at work."
    },
    {
      "type": "heading",
      "level": 2,
      "text": "Looking Ahead"
    },
    {
      "type": "paragraph",
      "text": "We have reviewed the definitions, graphs, identities, and applications of the trigonometric functions. These tools are not ornamental\u2014they are load-bearing. In the chapters ahead, we will:"
    },
    {
      "type": "list",
      "ordered": false,
      "items": [
        "Compute $\\lim_{x \\to 0}\\frac{\\sin x}{x}$ and use it to differentiate $\\sin x$ and $\\cos x$ from the definition (Chapter 3).",
        "Develop the derivatives of all six trigonometric functions (Chapter 4).",
        "Use inverse trig functions to evaluate integrals such as $\\int \\frac{1}{\\sqrt{1 - x^{2}}}\\,dx$ (Chapter 7).",
        "Master trigonometric substitution and the integration of powers of sine and cosine (Chapter 8)."
      ]
    },
    {
      "type": "paragraph",
      "text": "Every identity in this section will earn its keep. Make sure these tools are sharp; you are going to need them."
    },
    {
      "type": "figure",
      "id": "fig-1.5-sin-cos-graphs",
      "src": "/figures/vol1/ch01/sec05-sin-cos-graphs.svg",
      "caption": "One full period of $y = \\sin x$ and $y = \\cos x$. Notice that $\\cos x = \\sin\\!\\left(x + \\frac{\\pi}{2}\\right)$: the cosine curve is the sine curve shifted $\\frac{\\pi}{2}$ units to the left.",
      "alt": "Figure: Sin Cos Graphs"
    },
    {
      "type": "figure",
      "id": "fig-1.5-tan-graph",
      "src": "/figures/vol1/ch01/sec05-tan-graph.svg",
      "caption": "The graph of $y = \\tan x$. Vertical asymptotes (dashed) occur at $x = \\frac{\\pi}{2} + n\\pi$ for every integer~$n$.",
      "alt": "Figure: Tan Graph"
    },
    {
      "type": "heading",
      "level": 2,
      "text": "Exercises"
    },
    {
      "type": "exercise",
      "id": "ex1.5.1",
      "number": "1",
      "problem": "Evaluate without a calculator: (a) $\\sin\\frac{\\pi}{3}$, (b) $\\cos\\frac{\\pi}{4}$, (c) $\\tan\\frac{\\pi}{6}$."
    },
    {
      "type": "exercise",
      "id": "ex1.5.2",
      "number": "2",
      "problem": "Evaluate without a calculator: (a) $\\cos\\frac{2\\pi}{3}$, (b) $\\sin\\frac{7\\pi}{6}$, (c) $\\tan\\frac{5\\pi}{4}$."
    },
    {
      "type": "exercise",
      "id": "ex1.5.3",
      "number": "3",
      "problem": "Evaluate without a calculator: (a) $\\sin(-\\frac{\\pi}{4})$, (b) $\\cos(-\\frac{5\\pi}{6})$, (c) $\\tan(-\\frac{\\pi}{3})$."
    },
    {
      "type": "exercise",
      "id": "ex1.5.4",
      "number": "4",
      "problem": "Evaluate without a calculator: (a) $\\sec\\frac{\\pi}{3}$, (b) $\\csc\\frac{\\pi}{6}$, (c) $\\cot\\frac{\\pi}{4}$."
    },
    {
      "type": "exercise",
      "id": "ex1.5.5",
      "number": "5",
      "problem": "Evaluate: (a) $\\sin\\frac{11\\pi}{6}$, (b) $\\cos\\frac{5\\pi}{3}$, (c) $\\tan\\frac{3\\pi}{4}$."
    },
    {
      "type": "exercise",
      "id": "ex1.5.6",
      "number": "6",
      "problem": "Complete the following table of values. Do not use a calculator.\n\n| $t$ | $0$ | $\\frac{\\pi}{6}$ | $\\frac{\\pi}{4}$ | $\\frac{\\pi}{3}$ | $\\frac{\\pi}{2}$ | $\\frac{2\\pi}{3}$ | $\\frac{3\\pi}{4}$ | $\\pi$ |\n|---|---|---|---|---|---|---|---|---|\n| $\\sin t$ | | | | | | | | |\n| $\\cos t$ | | | | | | | | |"
    },
    {
      "type": "exercise",
      "id": "ex1.5.7",
      "number": "7",
      "problem": "Sketch one full period of $y = \\sin x$ and label all intercepts, maxima, and minima with their coordinates."
    },
    {
      "type": "exercise",
      "id": "ex1.5.8",
      "number": "8",
      "problem": "Sketch one full period of $y = \\cos x$ and label all intercepts, maxima, and minima with their coordinates."
    },
    {
      "type": "exercise",
      "id": "ex1.5.9",
      "number": "9",
      "problem": "For each function, state the amplitude, period, phase shift, and vertical shift:\n\n**(a)** $y = 2\\sin(3x)$\n\n**(b)** $y = -\\cos\\left(x - \\frac{\\pi}{4}\\right) + 3$\n\n**(c)** $y = \\frac{1}{2}\\sin(2x + \\pi) - 1$"
    },
    {
      "type": "exercise",
      "id": "ex1.5.10",
      "number": "10",
      "problem": "Sketch one full period of $y = 2\\sin\\left(x - \\frac{\\pi}{2}\\right)$, labeling the key points."
    },
    {
      "type": "exercise",
      "id": "ex1.5.11",
      "number": "11",
      "problem": "Sketch one full period of $y = -3\\cos(2x) + 1$, labeling the key points."
    },
    {
      "type": "exercise",
      "id": "ex1.5.12",
      "number": "12",
      "problem": "The graph of a sinusoidal function has maximum value 5, minimum value $-1$, and period $4\\pi$. If the maximum occurs at $x = \\pi$, write a possible formula for the function."
    },
    {
      "type": "exercise",
      "id": "ex1.5.13",
      "number": "13",
      "problem": "Sketch one full period of $y = \\tan x$ for $x \\in (-\\frac{\\pi}{2}, \\frac{\\pi}{2})$, labeling the asymptotes and the point where the graph crosses the origin."
    },
    {
      "type": "exercise",
      "id": "ex1.5.14",
      "number": "14",
      "problem": "Sketch one full period of $y = \\sec x$. *Hint:* Start by sketching $y = \\cos x$ lightly, then take reciprocals."
    },
    {
      "type": "exercise",
      "id": "ex1.5.15",
      "number": "15",
      "problem": "Use a Pythagorean identity to simplify $\\dfrac{\\sin^{2}\\theta}{1 - \\cos^{2}\\theta}$."
    },
    {
      "type": "exercise",
      "id": "ex1.5.16",
      "number": "16",
      "problem": "Simplify $\\cos^{2} x - \\sin^{2} x$ using a double-angle formula."
    },
    {
      "type": "exercise",
      "id": "ex1.5.17",
      "number": "17",
      "problem": "Verify the identity: $\\tan\\theta + \\cot\\theta = \\sec\\theta\\csc\\theta$."
    },
    {
      "type": "exercise",
      "id": "ex1.5.18",
      "number": "18",
      "problem": "Verify the identity: $\\dfrac{1 - \\cos 2\\alpha}{1 + \\cos 2\\alpha} = \\tan^{2}\\alpha$.",
      "challenging": true
    },
    {
      "type": "exercise",
      "id": "ex1.5.19",
      "number": "19",
      "problem": "Use the sum formula to find the exact value of $\\sin\\frac{7\\pi}{12}$. *Hint:* $\\frac{7\\pi}{12} = \\frac{\\pi}{3} + \\frac{\\pi}{4}$."
    },
    {
      "type": "exercise",
      "id": "ex1.5.20",
      "number": "20",
      "problem": "Use the sum formula to find the exact value of $\\cos 75\u00b0$. *Hint:* $75\u00b0 = 45\u00b0 + 30\u00b0$."
    },
    {
      "type": "exercise",
      "id": "ex1.5.21",
      "number": "21",
      "problem": "Show that $\\sin(x + y)\\sin(x - y) = \\sin^{2} x - \\sin^{2} y$.",
      "challenging": true
    },
    {
      "type": "exercise",
      "id": "ex1.5.22",
      "number": "22",
      "problem": "Find all solutions in $[0, 2\\pi)$: $2\\sin x - 1 = 0$."
    },
    {
      "type": "exercise",
      "id": "ex1.5.23",
      "number": "23",
      "problem": "Find all solutions in $[0, 2\\pi)$: $\\cos^{2}\\theta = \\frac{1}{2}$."
    },
    {
      "type": "exercise",
      "id": "ex1.5.24",
      "number": "24",
      "problem": "Find all solutions in $[0, 2\\pi)$: $2\\sin^{2} x + \\sin x - 1 = 0$."
    },
    {
      "type": "exercise",
      "id": "ex1.5.25",
      "number": "25",
      "problem": "Find all solutions in $[0, 2\\pi)$: $\\sin 2x = \\cos x$.",
      "challenging": true
    },
    {
      "type": "exercise",
      "id": "ex1.5.26",
      "number": "26",
      "problem": "Evaluate: (a) $\\arcsin\\left(\\frac{1}{2}\\right)$, (b) $\\arccos\\left(-\\frac{\\sqrt{2}}{2}\\right)$, (c) $\\arctan(\\sqrt{3})$."
    },
    {
      "type": "exercise",
      "id": "ex1.5.27",
      "number": "27",
      "problem": "Evaluate: (a) $\\sin(\\arccos\\frac{3}{5})$, (b) $\\cos(\\arctan 2)$. *Hint:* Draw a right triangle."
    },
    {
      "type": "exercise",
      "id": "ex1.5.28",
      "number": "28",
      "problem": "A weight on a spring oscillates with amplitude 10 cm and period 2 seconds. If the weight starts at its highest point, write a function $y(t)$ for the displacement from the rest position."
    },
    {
      "type": "exercise",
      "id": "ex1.5.29",
      "number": "29",
      "problem": "The depth of water in a harbor is modeled by\n$$D(t) = 8 + 4\\cos\\left(\\frac{\\pi}{6}\\,t\\right),$$\nwhere $D$ is in feet and $t$ is the number of hours after midnight.\n\n**(a)** What is the maximum depth, and when does it first occur?\n\n**(b)** What is the period of the tide?\n\n**(c)** At what times (in the first 24 hours) is the depth exactly 8 feet?",
      "creation_reveals": true
    },
    {
      "type": "exercise",
      "id": "ex1.5.30",
      "number": "30",
      "problem": "In Anchorage, Alaska, the number of hours of daylight on day $t$ (with $t = 1$ corresponding to January 1) is approximately\n$$H(t) = 12.15 + 6.55\\sin\\left(\\frac{2\\pi}{365}(t - 80)\\right).$$\n\n**(a)** What are the longest and shortest days, and how many hours of daylight does each have?\n\n**(b)** On what days does Anchorage have exactly 12.15 hours of daylight?",
      "creation_reveals": true
    },
    {
      "type": "exercise",
      "id": "ex1.5.31",
      "number": "31",
      "problem": "A Ferris wheel has a diameter of 40 meters and its center is 25 meters above the ground. It completes one revolution every 3 minutes. Write a sinusoidal function $h(t)$ for a rider's height above the ground (in meters) $t$ minutes after boarding at the lowest point."
    },
    {
      "type": "exercise",
      "id": "ex1.5.32",
      "number": "32",
      "problem": "A musical note \"A above middle C\" has a frequency of 440 Hz, meaning the sound wave completes 440 cycles per second. If the sound pressure variation has amplitude 0.02 pascals, write a sinusoidal model $p(t)$ for the pressure variation at time $t$ (in seconds).",
      "challenging": true,
      "creation_reveals": true
    },
    {
      "type": "exercise",
      "id": "ex1.5.33",
      "number": "33",
      "problem": "Prove that $\\sin^{2} t + \\cos^{2} t = 1$ using the unit-circle definition of sine and cosine.",
      "proof": true
    },
    {
      "type": "exercise",
      "id": "ex1.5.34",
      "number": "34",
      "problem": "Use the identity $\\sin^{2} t + \\cos^{2} t = 1$ to derive the identity $1 + \\tan^{2} t = \\sec^{2} t$. State clearly any restrictions on $t$.",
      "proof": true
    },
    {
      "type": "exercise",
      "id": "ex1.5.35",
      "number": "35",
      "problem": "A function $f$ is *periodic with period $T$* if $f(x + T) = f(x)$ for all $x$. Suppose $f$ has period $T$ and $g$ has period $S$. Is $f + g$ necessarily periodic? If so, find its period; if not, give a counterexample. *Hint:* Consider $f(x) = \\sin x$ and $g(x) = \\sin(\\sqrt{2}\\,x)$.",
      "challenging": true
    }
  ]
}