{
  "id": "diff-eq-ch06-sec03",
  "title": "Operational Properties I: Shifting Theorems",
  "chapter": 6,
  "section": 3,
  "book": "diff-eq",
  "content": [
    {
      "type": "paragraph",
      "text": "The power of the Laplace transform lies not just in the transforms of basic \nfunctions, but in the *operational properties* that allow us to \nbuild transforms of more complex functions from simpler ones. In this \nsection, we study the two fundamental shifting theorems."
    },
    {
      "type": "heading",
      "level": 2,
      "text": "The First Shifting Theorem ({$s$"
    },
    {
      "type": "paragraph",
      "text": "{s}-Shifting)}"
    },
    {
      "type": "theorem",
      "id": "theorem-6.1",
      "number": "6.1",
      "title": "First Shifting Theorem",
      "content": "If $\\mathcal{L}\\{f(t)\\} = F(s)$ for $s > \\alpha$, then\n\\[\n\\mathcal{L}\\{e^{at}f(t)\\} = F(s-a) \\quad \\text{for } s > \\alpha + a\n\\]\nEquivalently, multiplication by $e^{at}$ in the $t$-domain corresponds to \na shift by $a$ in the $s$-domain.",
      "label": "Theorem"
    },
    {
      "type": "proof",
      "content": "By definition:\n$$\n\\mathcal{L}\\{e^{at}f(t)\\} &= \\int_0^{\\infty} e^{-st} e^{at} f(t)\\,dt \\\\\n&= \\int_0^{\\infty} e^{-(s-a)t} f(t)\\,dt \\\\\n&= F(s-a) \\qedhere\n$$"
    },
    {
      "type": "remark",
      "id": "remark-6.3",
      "number": null,
      "title": "",
      "content": "This theorem is often stated as: \"To find $\\mathcal{L}\\{e^{at}f(t)\\}$, \nfirst find $\\mathcal{L}\\{f(t)\\} = F(s)$, then replace $s$ by $s - a$.\""
    },
    {
      "type": "example",
      "id": "example-6.1",
      "number": "6.1",
      "title": "Transform of $e^{at}t^n$",
      "problem": "Find $\\mathcal{L}\\{e^{3t}t^2\\}$.\n\n**Solution.** We know $\\mathcal{L}\\{t^2\\} = \\frac{2}{s^3}$. By the \nfirst shifting theorem with $a = 3$:\n\\[\n\\mathcal{L}\\{e^{3t}t^2\\} = \\frac{2}{(s-3)^3}, \\quad s > 3\n\\]",
      "solution": ""
    },
    {
      "type": "example",
      "id": "example-6.2",
      "number": "6.2",
      "title": "Transform of $e^{at}\\sin(bt)$",
      "problem": "Find $\\mathcal{L}\\{e^{-2t}\\sin(5t)\\}$.\n\n**Solution.** We have $\\mathcal{L}\\{\\sin(5t)\\} = \\frac{5}{s^2 + 25}$. \nBy the first shifting theorem with $a = -2$:\n\\[\n\\mathcal{L}\\{e^{-2t}\\sin(5t)\\} = \\frac{5}{(s+2)^2 + 25} = \\frac{5}{s^2 + 4s + 29}\n\\]",
      "solution": ""
    },
    {
      "type": "example",
      "id": "example-6.3",
      "number": "6.3",
      "title": "Transform of $e^{at}\\cos(bt)$",
      "problem": "Find $\\mathcal{L}\\{e^{2t}\\cos(3t)\\}$.\n\n**Solution.** We have $\\mathcal{L}\\{\\cos(3t)\\} = \\frac{s}{s^2 + 9}$. \nBy the first shifting theorem with $a = 2$:\n\\[\n\\mathcal{L}\\{e^{2t}\\cos(3t)\\} = \\frac{s-2}{(s-2)^2 + 9} = \\frac{s-2}{s^2 - 4s + 13}\n\\]",
      "solution": ""
    },
    {
      "type": "example",
      "id": "example-6.4",
      "number": "6.4",
      "title": "A more complex example",
      "problem": "Find $\\mathcal{L}\\{e^{-t}(t^2 + 3t - 1)\\}$.\n\n**Solution.** First, find the transform of $t^2 + 3t - 1$:\n\\[\n\\mathcal{L}\\{t^2 + 3t - 1\\} = \\frac{2}{s^3} + \\frac{3}{s^2} - \\frac{1}{s}\n\\]\nNow apply the first shifting theorem with $a = -1$ (replace $s$ by $s + 1$):\n\\[\n\\mathcal{L}\\{e^{-t}(t^2 + 3t - 1)\\} = \\frac{2}{(s+1)^3} + \\frac{3}{(s+1)^2} - \\frac{1}{s+1}\n\\]",
      "solution": ""
    },
    {
      "type": "heading",
      "level": 2,
      "text": "Standard Forms for Damped Oscillations"
    },
    {
      "type": "paragraph",
      "text": "The first shifting theorem gives us important transforms for damped \noscillations, which arise frequently in mechanical and electrical systems:"
    },
    {
      "type": "table",
      "headers": [
        "$f(t)$",
        "$F(s) = \\mathcal{L}\\{f(t)\\}$"
      ],
      "rows": [
        [
          "$e^{at}\\sin(bt)$",
          "$\\displaystyle\\frac{b}{(s-a)^2 + b^2}$"
        ],
        [
          "$e^{at}\\cos(bt)$",
          "$\\displaystyle\\frac{s-a}{(s-a)^2 + b^2}$"
        ],
        [
          "$e^{at}t^n$",
          "$\\displaystyle\\frac{n!}{(s-a)^{n+1}}$"
        ],
        [
          "$e^{at}\\sinh(bt)$",
          "$\\displaystyle\\frac{b}{(s-a)^2 - b^2}$"
        ],
        [
          "$e^{at}\\cosh(bt)$",
          "$\\displaystyle\\frac{s-a}{(s-a)^2 - b^2}$"
        ]
      ],
      "alignment": [
        "left",
        "left"
      ]
    },
    {
      "type": "heading",
      "level": 2,
      "text": "The Second Shifting Theorem ({$t$"
    },
    {
      "type": "paragraph",
      "text": "{t}-Shifting)}"
    },
    {
      "type": "paragraph",
      "text": "Before stating the second shifting theorem, we need to define the unit \nstep function."
    },
    {
      "type": "definition",
      "id": "definition-6.1",
      "number": "6.1",
      "title": "Unit Step Function (Heaviside Function)",
      "content": "The **unit step function** (or **Heaviside function**) $u(t)$ is defined by\n\\[\nu(t) = \\begin{cases} 0 & t < 0 \\\\ 1 & t \\geq 0 \\end{cases}\n\\]\nMore generally, the shifted unit step function $u(t-a)$ for $a \\geq 0$ is\n\\[\nu(t-a) = \\begin{cases} 0 & t < a \\\\ 1 & t \\geq a \\end{cases}\n\\]\nThis function \"turns on\" at time $t = a$."
    },
    {
      "type": "theorem",
      "id": "theorem-6.2",
      "number": "6.2",
      "title": "Laplace Transform of the Heaviside Function",
      "content": "For $a \\geq 0$ and $s > 0$,\n\\[\n\\mathcal{L}\\{u(t-a)\\} = \\frac{e^{-as}}{s}\n\\]\nIn particular, $\\mathcal{L}\\{u(t)\\} = \\mathcal{L}\\{1\\} = 1/s$.",
      "label": "Theorem"
    },
    {
      "type": "proof",
      "content": "$$\n\\mathcal{L}\\{u(t-a)\\} &= \\int_0^{\\infty} e^{-st} u(t-a)\\,dt \\\\\n&= \\int_a^{\\infty} e^{-st}\\,dt \\quad \\text{(since __MATH_BLOCK_0__ for __MATH_BLOCK_1__)} \\\\\n&= \\left[-\\frac{e^{-st}}{s}\\right]_a^{\\infty} = \\frac{e^{-as}}{s} \\qedhere\n$$"
    },
    {
      "type": "theorem",
      "id": "theorem-6.3",
      "number": "6.3",
      "title": "Second Shifting Theorem",
      "content": "If $\\mathcal{L}\\{f(t)\\} = F(s)$, then for $a \\geq 0$,\n\\[\n\\mathcal{L}\\{f(t-a)u(t-a)\\} = e^{-as}F(s)\n\\]\nEquivalently, a shift by $a$ in the $t$-domain corresponds to multiplication \nby $e^{-as}$ in the $s$-domain.",
      "label": "Theorem"
    },
    {
      "type": "proof",
      "content": "$$\n\\mathcal{L}\\{f(t-a)u(t-a)\\} &= \\int_0^{\\infty} e^{-st} f(t-a)u(t-a)\\,dt \\\\\n&= \\int_a^{\\infty} e^{-st} f(t-a)\\,dt\n$$\nLet $\\tau = t - a$, so $t = \\tau + a$ and $dt = d\\tau$. When $t = a$, $\\tau = 0$; \nwhen $t \\to \\infty$, $\\tau \\to \\infty$:\n$$\n&= \\int_0^{\\infty} e^{-s(\\tau + a)} f(\\tau)\\,d\\tau \\\\\n&= e^{-as} \\int_0^{\\infty} e^{-s\\tau} f(\\tau)\\,d\\tau \\\\\n&= e^{-as} F(s) \\qedhere\n$$"
    },
    {
      "type": "remark",
      "id": "remark-6.3",
      "number": null,
      "title": "",
      "content": "The factor $u(t-a)$ is essential. It ensures that $f(t-a)u(t-a) = 0$ for \n$t < a$, giving a function defined for all $t \\geq 0$."
    },
    {
      "type": "example",
      "id": "example-6.5",
      "number": "6.5",
      "title": "Applying the second shifting theorem",
      "problem": "Find $\\mathcal{L}\\{(t-3)^2 u(t-3)\\}$.\n\n**Solution.** Here $f(t) = t^2$, so $f(t-3) = (t-3)^2$. We have \n$\\mathcal{L}\\{t^2\\} = \\frac{2}{s^3}$. By the second shifting theorem:\n\\[\n\\mathcal{L}\\{(t-3)^2 u(t-3)\\} = e^{-3s} \\cdot \\frac{2}{s^3} = \\frac{2e^{-3s}}{s^3}\n\\]",
      "solution": ""
    },
    {
      "type": "example",
      "id": "example-6.6",
      "number": "6.6",
      "title": "Shifted sine function",
      "problem": "Find $\\mathcal{L}\\{\\sin(2(t-\\pi))u(t-\\pi)\\}$.\n\n**Solution.** Here $f(t) = \\sin(2t)$, $a = \\pi$. We have \n$\\mathcal{L}\\{\\sin(2t)\\} = \\frac{2}{s^2+4}$. By the second shifting theorem:\n\\[\n\\mathcal{L}\\{\\sin(2(t-\\pi))u(t-\\pi)\\} = e^{-\\pi s} \\cdot \\frac{2}{s^2+4} = \\frac{2e^{-\\pi s}}{s^2+4}\n\\]",
      "solution": ""
    },
    {
      "type": "heading",
      "level": 2,
      "text": "Rewriting Functions for the Second Shifting Theorem"
    },
    {
      "type": "paragraph",
      "text": "Often a function is not given in the form $f(t-a)u(t-a)$. We must rewrite \nit appropriately."
    },
    {
      "type": "example",
      "id": "example-6.7",
      "number": "6.7",
      "title": "Rewriting before applying the theorem",
      "problem": "Find $\\mathcal{L}\\{t^2 u(t-2)\\}$.\n\n**Solution.** Note that $t^2$ is *not* of the form $f(t-2)$ \nfor any simple function $f$. We rewrite:\n\\[\nt^2 = [(t-2) + 2]^2 = (t-2)^2 + 4(t-2) + 4\n\\]\nTherefore:\n$$\nt^2 u(t-2) &= [(t-2)^2 + 4(t-2) + 4]u(t-2) \\\\\n&= (t-2)^2 u(t-2) + 4(t-2)u(t-2) + 4u(t-2)\n$$\nNow apply the second shifting theorem to each term:\n$$\n\\mathcal{L}\\{t^2 u(t-2)\\} &= e^{-2s}\\mathcal{L}\\{t^2\\} + 4e^{-2s}\\mathcal{L}\\{t\\} + 4e^{-2s}\\mathcal{L}\\{1\\} \\\\\n&= e^{-2s}\\left(\\frac{2}{s^3} + \\frac{4}{s^2} + \\frac{4}{s}\\right)\n$$",
      "solution": ""
    },
    {
      "type": "example",
      "id": "example-6.8",
      "number": "6.8",
      "title": "A piecewise function",
      "problem": "Find the Laplace transform of\n\\[\nf(t) = \\begin{cases} 0 & 0 \\leq t < 1 \\\\ t - 1 & 1 \\leq t < 2 \\\\ 1 & t \\geq 2 \\end{cases}\n\\]\n\n**Solution.** We can write this using step functions:\n\\[\nf(t) = (t-1)u(t-1) - (t-2)u(t-2)\n\\]\nTo verify: for $t < 1$, both terms are zero. For $1 \\leq t < 2$, the first \nterm gives $t-1$ and the second is zero. For $t \\geq 2$, the first term \ngives $t-1$ and the second gives $-(t-2)$, so $f(t) = (t-1)-(t-2) = 1$. $\\checkmark$\n\nNow apply the second shifting theorem:\n$$\n\\mathcal{L}\\{f(t)\\} &= \\mathcal{L}\\{(t-1)u(t-1)\\} - \\mathcal{L}\\{(t-2)u(t-2)\\} \\\\\n&= e^{-s} \\cdot \\frac{1}{s^2} - e^{-2s} \\cdot \\frac{1}{s^2} \\\\\n&= \\frac{e^{-s} - e^{-2s}}{s^2}\n$$",
      "solution": ""
    },
    {
      "type": "heading",
      "level": 2,
      "text": "Comparison of the Two Shifting Theorems"
    },
    {
      "type": "table",
      "headers": [
        "",
        "**First Shifting**",
        "**Second Shifting**"
      ],
      "rows": [
        [
          "",
          "($s$-Shifting)",
          "($t$-Shifting)"
        ],
        [
          "Operation in $t$-domain",
          "Multiply by $e^{at}$",
          "Shift by $a$ (and use $u(t-a)$)"
        ],
        [
          "Operation in $s$-domain",
          "Replace $s$ by $s - a$",
          "Multiply by $e^{-as}$"
        ],
        [
          "Formula",
          "$\\mathcal{L}\\{e^{at}f(t)\\} = F(s-a)$",
          "$\\mathcal{L}\\{f(t-a)u(t-a)\\} = e^{-as}F(s)$"
        ]
      ],
      "alignment": [
        "left",
        "left",
        "left"
      ]
    },
    {
      "type": "example",
      "id": "example-6.9",
      "number": "6.9",
      "title": "Distinguishing the theorems",
      "problem": "Compare: (a) $\\mathcal{L}\\{e^{2t}\\sin(3t)\\}$ and (b) $\\mathcal{L}\\{\\sin(3(t-2))u(t-2)\\}$.\n\n**Solution.**\n\n(a) This is multiplication by $e^{2t}$, so use the first shifting theorem:\n\\[\n\\mathcal{L}\\{e^{2t}\\sin(3t)\\} = \\frac{3}{(s-2)^2 + 9}\n\\]\n\n(b) This is a shift by $2$ in time, so use the second shifting theorem:\n\\[\n\\mathcal{L}\\{\\sin(3(t-2))u(t-2)\\} = e^{-2s} \\cdot \\frac{3}{s^2 + 9} = \\frac{3e^{-2s}}{s^2+9}\n\\]",
      "solution": ""
    }
  ]
}