{
  "id": "precalculus-ch01-sec06",
  "title": "Inverse Functions",
  "chapter": 1,
  "section": 6,
  "book": "precalculus",
  "objectives": [
    "Determine whether a function is one-to-one using the horizontal line test",
    "Find the inverse of a one-to-one function algebraically",
    "Verify that two functions are inverses of each other",
    "Graph a function and its inverse on the same axes",
    "Find the domain and range of an inverse function"
  ],
  "epigraph": {
    "text": "*\"What has been will be again, what has been done will \nbe done again; there is nothing new under the sun.\"*",
    "reference": "Ecclesiastes 1:9",
    "quote": "To every action there is always opposed an equal reaction.",
    "quoteAuthor": "Isaac Newton",
    "edition": "christian"
  },
  "content": [
    {
      "type": "paragraph",
      "text": "Some functions can be \"undone.\" If a function $f$ takes an input $a$ \nand produces an output $b$, the inverse function takes $b$ back to $a$. \nThis concept is fundamental to solving equations and will be essential \nwhen we study logarithms and inverse trigonometric functions."
    },
    {
      "type": "heading",
      "level": 2,
      "text": "One-to-One Functions"
    },
    {
      "type": "paragraph",
      "text": "Not every function has an inverse. For a function to be reversible, \ndifferent inputs must produce different outputs."
    },
    {
      "type": "definition",
      "id": "ch01-sec06-definition-1.1",
      "title": "One-to-One Function",
      "content": "A function $f$ is **one-to-one** (or \n**injective**) if whenever $a \\neq b$, we have $f(a) \\neq f(b)$.\n\nEquivalently, $f$ is one-to-one if $f(a) = f(b)$ implies $a = b$.",
      "number": "1.1"
    },
    {
      "type": "theorem",
      "id": "ch01-sec06-theorem-1.1",
      "title": "Horizontal Line Test",
      "content": "A function is one-to-one if and only if every horizontal line intersects \nits graph at most once.",
      "number": "1.1"
    },
    {
      "type": "figure",
      "id": "fig:horizontal-line-test",
      "src": "/figures/precalculus/ch01/fig-horizontal-line-test.svg",
      "caption": "Horizontal line test for one-to-one functions. (a) Linear function passes: every horizontal line intersects at most once. (b) Parabola fails: the dashed horizontal line at $y = 2$ intersects twice, at $x \\approx \\pm 1.41$.",
      "alt": "Horizontal line test for one-to-one functions. (a) Linear function passes: every horizontal line intersects at most once. (b) Parabola fails: the dashed horizontal line at $y = 2$ intersects twice, at $x \\approx \\pm 1.41$.",
      "tikz": true
    },
    {
      "type": "example",
      "id": "ch01-sec06-example-1.1",
      "number": "1.1",
      "title": "Testing for one-to-one",
      "problem": "Determine whether each function is one-to-one.\n\n1. $f(x) = 2x + 5$\n\n2. $g(x) = x^2$\n\n3. $h(x) = x^3$",
      "solution": "1. **Yes.** Suppose $f(a) = f(b)$:\n $$\n 2a + 5 = 2b + 5 \\implies 2a = 2b \\implies a = b\n $$\n The function is one-to-one.\n\n2. **No.** We have $g(-2) = 4 = g(2)$, but $-2 \\neq 2$. \n Different inputs give the same output.\n\n3. **Yes.** Suppose $h(a) = h(b)$:\n $$\n a^3 = b^3 \\implies a = b\n $$\n (since the cube root is unique). The function is one-to-one."
    },
    {
      "type": "heading",
      "level": 2,
      "text": "The Inverse of a Function"
    },
    {
      "type": "definition",
      "id": "ch01-sec06-definition-1.2",
      "title": "Inverse Function",
      "content": "Let $f$ be a one-to-one function with domain $A$ and range $B$. The \n**inverse function** $f^{-1}$ has domain $B$ \nand range $A$, and is defined by\n$$\n f^-1(y) = x \\quad \\textif and only if \\quad f(x) = y\n$$\nfor all $y$ in $B$.",
      "number": "1.2"
    },
    {
      "type": "warning",
      "id": "ch01-sec06-warning-1",
      "title": "Notation Confusion: $f^{-1}$ vs $\\frac1{f}$",
      "content": "$f^-1(x)$ means the inverse function, NOT $\\frac1{f(x)}$.\nFor example, $\\sin^-1(x) \\neq \\frac1{\\sin x}$ (that's $\\csc x$)."
    },
    {
      "type": "paragraph",
      "text": "The inverse function \"undoes\" what $f$ does. If $f$ takes $a$ to $b$, \nthen $f^{-1}$ takes $b$ back to $a$."
    },
    {
      "type": "remark",
      "id": "ch01-sec06-remark-1",
      "title": "Building Intuition for Inverses",
      "content": "Think of each operation and its \"opposite\":\n\n- If $f$ **adds 3**, then $f^{-1}$ **subtracts 3**.\n\n- If $f$ **multiplies by 5**, then $f^{-1}$ **divides by 5**.\n\n- If $f$ **cubes**, then $f^{-1}$ takes the **cube root**.\n\n- If $f$ does \"multiply by 2, then add 7,\" then $f^{-1}$ does the operations in *reverse order*: \"subtract 7, then divide by 2.\"\nFor compound operations, the inverse reverses *both the operations and their order*—like taking off socks and shoes in the opposite order you put them on."
    },
    {
      "type": "paragraph",
      "text": "This relationship is captured by \nthe equations:\n$$\\beginaligned\n f^-1(f(x)) &= x \\quad \\textfor all x \\text in the domain of f \\\\\n f(f^-1(y)) &= y \\quad \\textfor all y \\text in the domain of f^-1\n\\end{aligned}$$"
    },
    {
      "type": "heading",
      "level": 2,
      "text": "Finding an Inverse Function"
    },
    {
      "type": "strategy",
      "id": "ch01-sec06-strategy-1",
      "title": "Finding the Inverse of a Function",
      "content": "1. Replace $f(x)$ with $y$\n\n2. Swap $x$ and $y$\n\n3. Solve for $y$\n\n4. Replace $y$ with $f^-1(x)$\n\n5. Verify: Check that $f(f^-1(x)) = x$"
    },
    {
      "type": "example",
      "id": "ch01-sec06-example-1.2",
      "number": "1.2",
      "title": "Finding an inverse",
      "problem": "Find the inverse of $f(x) = 3x - 7$.",
      "solution": "**Step 1:** Write $y = 3x - 7$.\n\n**Step 2:** Solve for $x$:\n$$\n y = 3x - 7 \\implies y + 7 = 3x \\implies x = \\fracy + 73\n$$\n\n**Step 3:** Replace $y$ with $x$:\n$$\n f^-1(x) = \\fracx + 73\n$$\n\n**Verification:**\n$$\n f(f^-1(x)) = f\\left(\\fracx + 73\\right) = 3 \\cdot \\fracx + 73 - 7 = x + 7 - 7 = x \\quad \\checkmark\n$$\n$$\n f^-1(f(x)) = f^-1(3x - 7) = \\frac(3x - 7) + 73 = \\frac3x3 = x \\quad \\checkmark\n$$"
    },
    {
      "type": "example",
      "id": "ch01-sec06-example-1.3",
      "number": "1.3",
      "title": "Finding an inverse with restricted domain",
      "problem": "Find the inverse of $f(x) = x^2$ for $x \\ge 0$.",
      "solution": "With the restriction $x \\ge 0$, the function is one-to-one.\n\n**Step 1:** Write $y = x^2$ with $x \\ge 0$.\n\n**Step 2:** Solve for $x$:\n$$\n y = x^2 \\implies x = \\sqrty \\quad \\text(taking the positive root since x \\ge 0\\text)\n$$\n\n**Step 3:** Replace $y$ with $x$:\n$$\n f^-1(x) = \\sqrtx\n$$\n\nThe domain of $f^{-1}$ is $[0, \\infty)$, which equals the range of $f$."
    },
    {
      "type": "heading",
      "level": 2,
      "text": "Graphs of Inverse Functions"
    },
    {
      "type": "theorem",
      "id": "ch01-sec06-theorem-1.2",
      "title": "Graph of an Inverse",
      "content": "The graph of $f^{-1}$ is the reflection of the graph of $f$ across the \nline $y = x$.",
      "number": "1.2"
    },
    {
      "type": "paragraph",
      "text": "This makes sense: if $(a, b)$ is on the graph of $f$ (meaning $f(a) = b$), \nthen $(b, a)$ is on the graph of $f^{-1}$ (meaning $f^-1(b) = a$). \nSwitching coordinates is exactly what reflection across $y = x$ does."
    },
    {
      "type": "figure",
      "id": "fig:inverse-reflection",
      "src": "/figures/precalculus/ch01/fig-inverse-reflection.svg",
      "caption": "Graph of $f$ and its inverse $f^{-1}$ reflected across the line $y = x$. If $(a, b)$ lies on the graph of $f$, then $(b, a)$ lies on the graph of $f^{-1}$. The dotted line shows this correspondence.",
      "alt": "Graph of $f$ and its inverse $f^{-1}$ reflected across the line $y = x$. If $(a, b)$ lies on the graph of $f$, then $(b, a)$ lies on the graph of $f^{-1}$. The dotted line shows this correspondence.",
      "tikz": true
    },
    {
      "type": "heading",
      "level": 2,
      "text": "Domain and Range of Inverse Functions"
    },
    {
      "type": "theorem",
      "id": "ch01-sec06-theorem-1.3",
      "title": "Domain and Range of Inverses",
      "content": "If $f$ has domain $A$ and range $B$, then $f^{-1}$ has domain $B$ and \nrange $A$. That is:\n\n- Domain of $f^{-1}$ = Range of $f$\n\n- Range of $f^{-1}$ = Domain of $f$",
      "number": "1.3"
    },
    {
      "type": "example",
      "id": "ch01-sec06-example-1.4",
      "number": "1.4",
      "title": "Domain and range of an inverse",
      "problem": "Let $f(x) = \\sqrt{x - 2}$. Find $f^{-1}$ and state its domain and range.",
      "solution": "First, note that $f$ has domain $[2, \\infty)$ and range $[0, \\infty)$.\n\nTo find $f^{-1}$:\n$$\n y = \\sqrtx - 2 \\implies y^2 = x - 2 \\implies x = y^2 + 2\n$$\n\nTherefore, $f^-1(x) = x^2 + 2$.\n\nBut we must restrict the domain: since the range of $f$ is $[0, \\infty)$, \nthe domain of $f^{-1}$ is $[0, \\infty)$.\n\n**Summary:**\n\n- $f^-1(x) = x^2 + 2$ with domain $[0, \\infty)$\n\n- Range of $f^{-1}$ is $[2, \\infty)$ (which equals the domain of $f$)"
    },
    {
      "type": "exercise",
      "id": "ch01-sec06-ex-1",
      "number": "1",
      "problem": "Fill in each blank with the appropriate term or expression.",
      "variant": "vocabulary"
    },
    {
      "type": "exercise",
      "id": "ch01-sec06-ex-2",
      "number": "2",
      "problem": "1. A function $f$ is if every horizontal line \n intersects its graph at most once.\n\n2. The line test determines whether a function \n has an inverse.\n\n3. If $f(a) = b$, then $f^-1(b) = $ .\n\n4. The notation $f^{-1}$ means the of $f$, \n not the of $f(x)$.\n\n5. $(f \\circ f^-1)(x) = $ and \n $(f^-1 \\circ f)(x) = $ .\n\n6. The graphs of $f$ and $f^{-1}$ are symmetric about the line \n $y = $ .\n\n7. If $f$ has domain $A$ and range $B$, then $f^{-1}$ has domain \n and range .",
      "variant": "regular"
    },
    {
      "type": "exercise",
      "id": "ch01-sec06-ex-3",
      "number": "3",
      "problem": "True or False? Justify your answer.",
      "variant": "conceptual"
    },
    {
      "type": "exercise",
      "id": "ch01-sec06-ex-4",
      "number": "4",
      "problem": "1. Every function has an inverse function.\n\n2. If $f(2) = 5$, then $f^-1(2) = 5$.\n\n3. The notation $f^-1(x)$ means $\\dfrac1{f(x)}$.\n\n4. If $f$ is strictly increasing on its domain, then $f$ has an inverse.\n\n5. The domain of $f$ equals the range of $f^{-1}$.\n\n6. If $f$ and $g$ are both one-to-one, then $f \\circ g$ is one-to-one.",
      "variant": "regular"
    },
    {
      "type": "exercise",
      "id": "ch01-sec06-ex-5",
      "number": "5",
      "problem": "Explain why $f(x) = x^2$ does not have an inverse over all real numbers, \nbut does have an inverse when its domain is restricted to $[0, \\infty)$.",
      "variant": "regular"
    },
    {
      "type": "exercise",
      "id": "ch01-sec06-ex-6",
      "number": "6",
      "problem": "Explain how the horizontal line test relates to the vertical line test. \nWhat does each test check for?",
      "variant": "regular"
    },
    {
      "type": "heading",
      "level": 3,
      "text": "Determining One-to-One Functions"
    },
    {
      "type": "exercise",
      "id": "ch01-sec06-ex-7",
      "number": "7",
      "problem": "1. $f(x) = 5x - 3$\n\n2. $g(x) = x^2 + 1$\n\n3. $h(x) = \\dfrac1{x}$\n\n4. $p(x) = |x|$",
      "variant": "regular"
    },
    {
      "type": "exercise",
      "id": "ch01-sec06-ex-8",
      "number": "8",
      "problem": "1. $f(x) = x^3$\n\n2. $g(x) = \\sqrt{x}$\n\n3. $h(x) = 3x - 7$\n\n4. $k(x) = x^2 - 4$",
      "variant": "regular"
    },
    {
      "type": "exercise",
      "id": "ch01-sec06-ex-9",
      "number": "9",
      "problem": "1. $f(x) = x^4$\n\n2. $g(x) = x^3 - x$\n\n3. $h(x) = 2^x$\n\n4. $k(x) = \\sqrt[3]{x - 1}$",
      "variant": "regular"
    },
    {
      "type": "exercise",
      "id": "ch01-sec06-ex-10",
      "number": "10",
      "problem": "1. $f(x) = x^3 + x$\n\n2. $g(x) = \\dfracx{x + 1}$\n\n3. $h(x) = x^2 - 4x$ on $[2, \\infty)$\n\n4. $k(x) = |x - 3|$",
      "variant": "regular"
    },
    {
      "type": "heading",
      "level": 3,
      "text": "Finding Inverse Functions"
    },
    {
      "type": "exercise",
      "id": "ch01-sec06-ex-11",
      "number": "11",
      "problem": "1. $f(x) = 4x + 7$\n\n2. $g(x) = \\dfracx - 2{3}$\n\n3. $h(x) = 5 - 2x$\n\n4. $k(x) = \\dfrac2x + 1{3}$",
      "variant": "regular"
    },
    {
      "type": "exercise",
      "id": "ch01-sec06-ex-12",
      "number": "12",
      "problem": "1. $f(x) = 3x - 5$\n\n2. $g(x) = \\dfracx + 4{2}$\n\n3. $h(x) = 7 - 3x$\n\n4. $k(x) = \\dfrac4 - x{3}$",
      "variant": "regular"
    },
    {
      "type": "exercise",
      "id": "ch01-sec06-ex-13",
      "number": "13",
      "problem": "1. $f(x) = 5x - 7$\n\n2. $g(x) = \\dfracx - 3{2}$\n\n3. $h(x) = 4x - 3$\n\n4. $k(x) = \\dfrac2x + 3{5}$",
      "variant": "regular"
    },
    {
      "type": "exercise",
      "id": "ch01-sec06-ex-14",
      "number": "14",
      "problem": "1. $f(x) = 2x + 5$\n\n2. $g(x) = \\dfracx - 1{4}$\n\n3. $h(x) = 6 - 5x$\n\n4. $k(x) = \\dfrac3x - 2{4}$",
      "variant": "regular"
    },
    {
      "type": "exercise",
      "id": "ch01-sec06-ex-15",
      "number": "15",
      "problem": "1. $f(x) = x^3$\n\n2. $g(x) = x^3 + 1$\n\n3. $h(x) = x^3 - 8$\n\n4. $k(x) = (x - 2)^3 + 1$",
      "variant": "regular"
    },
    {
      "type": "exercise",
      "id": "ch01-sec06-ex-16",
      "number": "16",
      "problem": "1. $f(x) = \\sqrt{x - 2}$\n\n2. $g(x) = \\sqrt{x + 5}$\n\n3. $h(x) = \\sqrtx + 1 - 2$\n\n4. $k(x) = \\sqrt{4 - x}$",
      "variant": "regular"
    },
    {
      "type": "exercise",
      "id": "ch01-sec06-ex-17",
      "number": "17",
      "problem": "1. $f(x) = \\sqrt[3]{x + 5}$\n\n2. $g(x) = \\sqrt[3]{x - 2}$\n\n3. $h(x) = \\sqrt[3]{2x - 1}$\n\n4. $k(x) = 2\\sqrt[3]x + 3$",
      "variant": "regular"
    },
    {
      "type": "exercise",
      "id": "ch01-sec06-ex-18",
      "number": "18",
      "problem": "1. $f(x) = x^5$\n\n2. $g(x) = \\sqrt[5]{x - 1}$\n\n3. $h(x) = (x + 3)^3 - 2$\n\n4. $k(x) = \\sqrt{x - 4}$",
      "variant": "regular"
    },
    {
      "type": "exercise",
      "id": "ch01-sec06-ex-19",
      "number": "19",
      "problem": "1. $f(x) = \\dfrac1{x}$\n\n2. $g(x) = \\dfrac1{x - 1}$\n\n3. $h(x) = \\dfrac2{x + 3}$\n\n4. $k(x) = \\dfrac1{x - 2}$",
      "variant": "regular"
    },
    {
      "type": "exercise",
      "id": "ch01-sec06-ex-20",
      "number": "20",
      "problem": "1. $f(x) = \\dfracx + 1{x - 1}$\n\n2. $g(x) = \\dfrac2x + 1{x - 3}$\n\n3. $h(x) = \\dfrac3x - 2{x + 4}$\n\n4. $k(x) = \\dfracx{2x + 1}$",
      "variant": "regular"
    },
    {
      "type": "exercise",
      "id": "ch01-sec06-ex-21",
      "number": "21",
      "problem": "1. $f(x) = \\dfrac2x + 3{x - 1}$\n\n2. $g(x) = \\dfracx + 5{2x - 3}$\n\n3. $h(x) = \\dfrac3x{x + 2}$\n\n4. $k(x) = \\dfracx{x - 1}$",
      "variant": "regular"
    },
    {
      "type": "exercise",
      "id": "ch01-sec06-ex-22",
      "number": "22",
      "problem": "1. $f(x) = \\dfrac2x - 1{x + 3}$\n\n2. $g(x) = \\dfrac4x + 1{2x - 5}$\n\n3. $h(x) = \\dfrac1x + 2 - 1$\n\n4. $k(x) = \\dfrac5 - 2x{3x + 1}$",
      "variant": "regular"
    },
    {
      "type": "exercise",
      "id": "ch01-sec06-ex-23",
      "number": "23",
      "problem": "1. $f(x) = x^2$, $x \\geq 0$\n\n2. $g(x) = x^2 - 4$, $x \\geq 0$\n\n3. $h(x) = (x - 2)^2$, $x \\geq 2$\n\n4. $k(x) = x^2 + 2x$, $x \\geq -1$",
      "variant": "regular"
    },
    {
      "type": "exercise",
      "id": "ch01-sec06-ex-24",
      "number": "24",
      "problem": "1. $f(x) = x^2 + 1$, $x \\leq 0$\n\n2. $g(x) = 4 - x^2$, $x \\geq 0$\n\n3. $h(x) = (x + 1)^2 - 3$, $x \\geq -1$\n\n4. $k(x) = (x - 3)^2 + 2$, $x \\leq 3$",
      "variant": "regular"
    },
    {
      "type": "exercise",
      "id": "ch01-sec06-ex-25",
      "number": "25",
      "problem": "1. $f(x) = x^2 + 3$, $x \\geq 0$\n\n2. $g(x) = (x + 2)^2$, $x \\leq -2$\n\n3. $h(x) = x^2 - 6x$, $x \\geq 3$\n\n4. $k(x) = |x - 1|$, $x \\geq 1$",
      "variant": "regular"
    },
    {
      "type": "exercise",
      "id": "ch01-sec06-ex-26",
      "number": "26",
      "problem": "For each function, (i) restrict the domain so that it is one-to-one, \nthen (ii) find the inverse on that domain.\n\n1. $f(x) = x^2 - 4$\n\n2. $g(x) = (x - 2)^2$\n\n3. $h(x) = |x - 1|$\n\n4. $k(x) = x^2 + 4x + 4$",
      "variant": "regular"
    },
    {
      "type": "heading",
      "level": 3,
      "text": "Verifying Inverse Functions"
    },
    {
      "type": "exercise",
      "id": "ch01-sec06-ex-27",
      "number": "27",
      "problem": "1. $f(x) = 3x + 1$, $g(x) = \\dfracx - 1{3}$\n\n2. $f(x) = 2x - 4$, $g(x) = \\dfracx + 4{2}$",
      "variant": "regular"
    },
    {
      "type": "exercise",
      "id": "ch01-sec06-ex-28",
      "number": "28",
      "problem": "1. $f(x) = x^3 - 2$, $g(x) = \\sqrt[3]{x + 2}$\n\n2. $f(x) = x^3 - 8$, $g(x) = \\sqrt[3]{x + 8}$",
      "variant": "regular"
    },
    {
      "type": "exercise",
      "id": "ch01-sec06-ex-29",
      "number": "29",
      "problem": "1. $f(x) = \\dfrac1{x + 1}$, $g(x) = \\dfrac1 - x{x}$\n\n2. $f(x) = \\dfracx + 2{x - 3}$, $g(x) = \\dfrac3x + 2{x - 1}$",
      "variant": "regular"
    },
    {
      "type": "exercise",
      "id": "ch01-sec06-ex-30",
      "number": "30",
      "problem": "1. $f(x) = \\sqrt{x + 1}$, $g(x) = x^2 - 1$ for $x \\geq 0$\n\n2. $f(x) = \\dfracx + 1{x - 1}$, $g(x) = \\dfracx + 1{x - 1}$",
      "variant": "regular"
    },
    {
      "type": "heading",
      "level": 3,
      "text": "Domain and Range"
    },
    {
      "type": "exercise",
      "id": "ch01-sec06-ex-31",
      "number": "31",
      "problem": "1. $f(x) = 2x + 6$\n\n2. $f(x) = \\sqrt{x - 3}$",
      "variant": "regular"
    },
    {
      "type": "exercise",
      "id": "ch01-sec06-ex-32",
      "number": "32",
      "problem": "1. $f(x) = x^2 + 1$, $x \\geq 0$\n\n2. $f(x) = \\dfrac1{x - 2}$",
      "variant": "regular"
    },
    {
      "type": "exercise",
      "id": "ch01-sec06-ex-33",
      "number": "33",
      "problem": "1. $f(x) = \\dfrac3x{x + 2}$\n\n2. $f(x) = \\sqrtx + 4 - 1$",
      "variant": "regular"
    },
    {
      "type": "exercise",
      "id": "ch01-sec06-ex-34",
      "number": "34",
      "problem": "If $f$ has domain $[0, 4]$ and range $[2, 10]$, what are the domain \nand range of $f^{-1}$?",
      "variant": "regular"
    },
    {
      "type": "heading",
      "level": 3,
      "text": "Finding Values from Inverse Relationships"
    },
    {
      "type": "exercise",
      "id": "ch01-sec06-ex-35",
      "number": "35",
      "problem": "The graph of a one-to-one function $f$ passes through the points \n$(1, 5)$, $(3, 2)$, and $(4, -1)$. Find:\n\n1. $f^-1(5)$\n\n2. $f^-1(2)$\n\n3. $f^-1(-1)$",
      "variant": "regular"
    },
    {
      "type": "exercise",
      "id": "ch01-sec06-ex-36",
      "number": "36",
      "problem": "Given that $f$ is one-to-one with $f(2) = 7$ and $f(5) = 3$:\n\n1. Find $f^-1(7)$\n\n2. Find $f^-1(3)$\n\n3. Find $(f^-1 \\circ f)(2)$",
      "variant": "regular"
    },
    {
      "type": "exercise",
      "id": "ch01-sec06-ex-37",
      "number": "37",
      "problem": "1. If $f(3) = 7$, find $f^-1(7)$.\n\n2. If $f^-1(5) = 2$, find $f(2)$.\n\n3. If $f(x) = 2x + 3$ and $f^-1(a) = 4$, find $a$.",
      "variant": "regular"
    },
    {
      "type": "exercise",
      "id": "ch01-sec06-ex-38",
      "number": "38",
      "problem": "If $f(2) = 5$ and $f(5) = 8$, find $f^-1(5)$ and $f^-1(8)$.",
      "variant": "regular"
    },
    {
      "type": "exercise",
      "id": "ch01-sec06-ex-39",
      "number": "39",
      "problem": "The graph of $f$ passes through $(2, 5)$. What point is on the graph of $f^{-1}$?",
      "variant": "regular"
    },
    {
      "type": "exercise",
      "id": "ch01-sec06-ex-40",
      "number": "40",
      "problem": "Given the graph of $f$:\n\n1. If $(3, 5)$ is on the graph of $f$, what point is on the graph of $f^{-1}$?\n\n2. If $f(7) = 2$, find $f^-1(2)$.\n\n3. If $f^-1(4) = -1$, find $f(-1)$.",
      "variant": "regular"
    },
    {
      "type": "exercise",
      "id": "ch01-sec06-ex-41",
      "number": "41",
      "problem": "Given the table of values for $f$, create a table for $f^{-1}$.\n| $x$ | $-2$ | $0$ | $2$ | $4$ | $6$ |\n| $f(x)$ | $1$ | $3$ | $5$ | $7$ | $9$ |",
      "variant": "regular"
    },
    {
      "type": "heading",
      "level": 3,
      "text": "Applications"
    },
    {
      "type": "exercise",
      "id": "ch01-sec06-ex-42",
      "number": "42",
      "problem": "The formula $F(C) = \\dfrac95C + 32$ converts Celsius to Fahrenheit.\n\n1. Find $F^{-1}$ and interpret what it computes.\n\n2. Use $F^{-1}$ to convert 98.6°F to Celsius.\n\n3. At what temperature are $F$ and $C$ equal?",
      "variant": "regular"
    },
    {
      "type": "exercise",
      "id": "ch01-sec06-ex-43",
      "number": "43",
      "problem": "A function converts U.S.\\ dollars to euros: $E(d) = 0.85d$.\n\n1. Find the inverse function.\n\n2. Use the inverse to convert 170 euros to dollars.\n\n3. Interpret the meaning of the inverse function.",
      "variant": "regular"
    },
    {
      "type": "exercise",
      "id": "ch01-sec06-ex-44",
      "number": "44",
      "problem": "An employee's annual salary after $y$ years is $S(y) = 45000 + 2000y$.\n\n1. Find $S^{-1}$ and interpret what it computes.\n\n2. How many years until the salary reaches $65,000?",
      "variant": "regular"
    },
    {
      "type": "exercise",
      "id": "ch01-sec06-ex-45",
      "number": "45",
      "problem": "A car's value after $t$ years is $V(t) = 25000(0.85)^t$.\n\n1. Find the inverse function.\n\n2. When will the car be worth $10,000?",
      "variant": "regular"
    },
    {
      "type": "exercise",
      "id": "ch01-sec06-ex-46",
      "number": "46",
      "problem": "The distance $d$ (in feet) that a ball falls in $t$ seconds is $d(t) = 16t^2$ \nfor $t \\geq 0$.\n\n1. Find the inverse function $t(d)$.\n\n2. How long does it take a ball to fall 64 feet?\n\n3. How long to fall 100 feet?",
      "variant": "regular"
    },
    {
      "type": "heading",
      "level": 3,
      "text": "Graphing Utility Exercises"
    },
    {
      "type": "exercise",
      "id": "ch01-sec06-ex-47",
      "number": "47",
      "problem": "Use a graphing utility to graph $f$ and $f^{-1}$ in the same \nviewing window along with the line $y = x$. Verify that the graphs are \nreflections of each other across $y = x$.",
      "variant": "technology"
    },
    {
      "type": "exercise",
      "id": "ch01-sec06-ex-48",
      "number": "48",
      "problem": "1. $f(x) = 3x - 2$\n\n2. $f(x) = \\dfrac12x + 3$\n\n3. $f(x) = x^3 + 1$",
      "variant": "regular"
    },
    {
      "type": "exercise",
      "id": "ch01-sec06-ex-49",
      "number": "49",
      "problem": "1. $f(x) = \\sqrt{x + 2}$\n\n2. $f(x) = x^2 - 1$ for $x \\geq 0$\n\n3. $f(x) = \\dfracx{x + 1}$",
      "variant": "regular"
    },
    {
      "type": "exercise",
      "id": "ch01-sec06-ex-50",
      "number": "50",
      "problem": "Graph $f(x) = x^2$ and $g(x) = \\sqrt{x}$ together. Explain \nwhy $g$ is the inverse of $f$ only for $x \\geq 0$.",
      "variant": "technology"
    },
    {
      "type": "heading",
      "level": 3,
      "text": "Error Analysis"
    },
    {
      "type": "exercise",
      "id": "ch01-sec06-ex-51",
      "number": "51",
      "problem": "Describe and correct the error in each solution.",
      "variant": "error-analysis"
    },
    {
      "type": "exercise",
      "id": "ch01-sec06-ex-52",
      "number": "52",
      "problem": "Finding the inverse of $f(x) = 2x + 3$:\n> \"$f^-1(x) = \\dfrac1{2x + 3}$\" ✗}",
      "variant": "regular"
    },
    {
      "type": "exercise",
      "id": "ch01-sec06-ex-53",
      "number": "53",
      "problem": "Finding the inverse of $f(x) = x^2$ for all real numbers:\n> \"$y = x^2$, so $x = \\sqrt{y}$, thus $f^-1(x) = \\sqrt{x}$\" \n ✗}",
      "variant": "regular"
    },
    {
      "type": "exercise",
      "id": "ch01-sec06-ex-54",
      "number": "54",
      "problem": "Finding the inverse of $f(x) = \\dfrac1{x - 3}$:\n> \"$y = \\dfrac1{x - 3}$, so $y(x - 3) = 1$, giving $x = \\dfrac1y + 3$. \nTherefore $f^-1(x) = \\dfrac1x + 3$ with domain all real numbers.\" \n ✗}",
      "variant": "regular"
    },
    {
      "type": "exercise",
      "id": "ch01-sec06-ex-55",
      "number": "55",
      "problem": "Evaluating $f^-1(4)$ for $f(x) = x^2 + 1$:\n> \"Since $f(x) = x^2 + 1$, we have $f^-1(x) = \\sqrt{x - 1}$. \nSo $f^-1(4) = \\sqrt{3}$.\" ✗}",
      "variant": "regular"
    },
    {
      "type": "heading",
      "level": 3,
      "text": "Challenge Problems"
    },
    {
      "type": "exercise",
      "id": "ch01-sec06-ex-56",
      "number": "56",
      "problem": "A function $f$ is called **self-inverse** (or **involutory**) \nif $f = f^{-1}$, meaning $f(f(x)) = x$.\n\n1. Show that $f(x) = \\dfrac1{x}$ is self-inverse.\n\n2. Show that $f(x) = \\dfracx + 1{x - 1}$ is self-inverse.\n\n3. Verify that $f(x) = -x$ is self-inverse.",
      "variant": "regular"
    },
    {
      "type": "exercise",
      "id": "ch01-sec06-ex-57",
      "number": "57",
      "problem": "Find all linear functions $f(x) = mx + b$ that are self-inverse.",
      "variant": "starred"
    },
    {
      "type": "exercise",
      "id": "ch01-sec06-ex-58",
      "number": "58",
      "problem": "If $f(x) = \\dfracax + b{cx + d}$ is its own inverse, find \nthe relationship between $a$, $b$, $c$, and $d$.",
      "variant": "starred"
    },
    {
      "type": "exercise",
      "id": "ch01-sec06-ex-59",
      "number": "59",
      "problem": "Prove that if $f$ is a strictly increasing function on its \ndomain, then $f$ is one-to-one.",
      "variant": "starred"
    },
    {
      "type": "exercise",
      "id": "ch01-sec06-ex-60",
      "number": "60",
      "problem": "Prove that if $f$ is one-to-one and increasing, then $f^{-1}$ \nis also increasing.",
      "variant": "starred"
    },
    {
      "type": "exercise",
      "id": "ch01-sec06-ex-61",
      "number": "61",
      "problem": "Prove that if $f$ is odd and has an inverse, then $f^{-1}$ \nis also odd.",
      "variant": "starred"
    },
    {
      "type": "exercise",
      "id": "ch01-sec06-ex-62",
      "number": "62",
      "problem": "Prove that if $f$ is one-to-one and has an inverse $f^{-1}$, \nthen $f^{-1}$ is also one-to-one and $(f^-1)^-1 = f$.",
      "variant": "starred"
    },
    {
      "type": "exercise",
      "id": "ch01-sec06-ex-63",
      "number": "63",
      "problem": "Prove that a function can have at most one inverse.\n\n\\beginatlassummarySection 1.6 Summary: Inverse Functions\n\n**Key Concepts:**\n\n- A function is **one-to-one** if $f(a) = f(b)$ implies $a = b$\n\n- Use the **horizontal line test**: $f$ is one-to-one iff every \n horizontal line intersects the graph at most once\n\n- The **inverse function** $f^{-1}$ satisfies: $f^-1(y) = x$ \n iff $f(x) = y$\n\n- **Verification**: $f(f^-1(x)) = x$ and $f^-1(f(x)) = x$",
      "variant": "starred"
    },
    {
      "type": "heading",
      "level": 3,
      "text": "Finding $f^{-1"
    },
    {
      "type": "heading",
      "level": 3,
      "text": "Domain/Range:"
    },
    {
      "type": "heading",
      "level": 3,
      "text": "Graphical Property:"
    }
  ],
  "marginNotes": [
    {
      "type": "scripture",
      "reference": "Isaiah 43:1",
      "text": "Fear not, for I have redeemed you; I have \ncalled you by name; you are mine.",
      "edition": "christian"
    }
  ]
}