{
  "id": "algebra-2-ch09-sec03",
  "title": "Sigma Notation and Special Series",
  "chapter": 9,
  "section": 3,
  "book": "algebra-2",
  "devotional": {
    "title": "The Golden Ratio",
    "scripture": "Ecclesiastes 3:11",
    "content": "{AtlasWarmH}{e}\nhas made everything beautiful in its time. He has also set eternity in \nthe human heart.\n\nThe ratio of consecutive Fibonacci numbers approaches the **golden \nratio** $\\phi = \\frac{1 + \\sqrt{5}}{2} \\approx 1.618$. This irrational \nnumber appears in the proportions of beautiful art and architecture, \nin the spiral of galaxies, and in the growth patterns of plants.\n\nThe golden ratio is connected to the Fibonacci sequence, which emerges \nfrom a simple rule: each term is the sum of the two before it. From \nsimple rules comes complex beauty.\n\nCreation displays mathematical elegance that humans find beautiful. The \nsame proportions appear in the Parthenon, in Renaissance paintings, and \nin the chambers of a nautilus shell. This \"divine proportion\" hints \nat a designing intelligence.",
    "reflection": "The Fibonacci sequence and golden ratio appear \nthroughout nature and art. What does this mathematical beauty suggest \nabout the Creator's nature and our capacity to recognize it?"
  },
  "epigraph": {
    "text": "Count the stars—if indeed you can count them.",
    "reference": "Genesis 15:5"
  },
  "content": [
    {
      "type": "paragraph",
      "text": "Sigma notation provides a compact way to write sums with many terms. \nThe Greek letter $\\Sigma$ (capital sigma) represents summation, \nallowing us to express complex sums in elegant form. This notation is \nessential for calculus, statistics, and advanced mathematics, where \nsums with hundreds or infinitely many terms are common."
    },
    {
      "type": "heading",
      "level": 2,
      "text": "Understanding Sigma Notation"
    },
    {
      "type": "definition",
      "id": "definition-9.1",
      "number": "9.1",
      "title": "Sigma Notation",
      "content": "The notation $\\displaystyle\\sum_{k=m}^{n} a_k$ represents the sum:\n\\[\n \\sum_{k=m}^{n} a_k = a_m + a_{m+1} + a_{m+2} + \\cdots + a_n\n\\]\nwhere:\n\n- $\\Sigma$ is the summation symbol\n\n- $k$ is the **index of summation** (dummy variable)\n\n- $m$ is the **lower limit**\n\n- $n$ is the **upper limit**\n\n- $a_k$ is the **general term**"
    },
    {
      "type": "paragraph",
      "text": "The index variable $k$ is a \"dummy variable\"—it can be replaced by \nany letter. The expressions $\\sum_{k=1}^{5} k^2$, $\\sum_{j=1}^{5} j^2$, \nand $\\sum_{i=1}^{5} i^2$ all represent the same sum: $1 + 4 + 9 + 16 + 25$."
    },
    {
      "type": "example",
      "id": "example-9.1",
      "number": "9.1",
      "title": "Evaluating sigma notation",
      "problem": "Evaluate each sum:\n\n1. $\\displaystyle\\sum_{k=1}^{5} k^2$\n\n2. $\\displaystyle\\sum_{j=0}^{4} 2^j$\n\n3. $\\displaystyle\\sum_{i=3}^{6} (2i - 1)$",
      "solution": "1. $\\displaystyle\\sum_{k=1}^{5} k^2 = 1^2 + 2^2 + 3^2 + 4^2 + 5^2 = 1 + 4 + 9 + 16 + 25 = 55$\n\n2. $\\displaystyle\\sum_{j=0}^{4} 2^j = 2^0 + 2^1 + 2^2 + 2^3 + 2^4 = 1 + 2 + 4 + 8 + 16 = 31$\n\n3. $\\displaystyle\\sum_{i=3}^{6} (2i - 1) = 5 + 7 + 9 + 11 = 32$"
    },
    {
      "type": "example",
      "id": "example-9.2",
      "number": "9.2",
      "title": "More evaluation practice",
      "problem": "Evaluate each sum:\n\n1. $\\displaystyle\\sum_{n=1}^{4} (3n + 2)$\n\n2. $\\displaystyle\\sum_{k=2}^{5} \\frac{1}{k}$\n\n3. $\\displaystyle\\sum_{i=0}^{3} (-1)^i \\cdot i$",
      "solution": "1. $\\displaystyle\\sum_{n=1}^{4} (3n + 2) = 5 + 8 + 11 + 14 = 38$\n\n2. $\\displaystyle\\sum_{k=2}^{5} \\frac{1}{k} = \\frac{1}{2} + \\frac{1}{3} + \\frac{1}{4} + \\frac{1}{5} = \\frac{30 + 20 + 15 + 12}{60} = \\frac{77}{60}$\n\n3. $\\displaystyle\\sum_{i=0}^{3} (-1)^i \\cdot i = (-1)^0 \\cdot 0 + (-1)^1 \\cdot 1 + (-1)^2 \\cdot 2 + (-1)^3 \\cdot 3$\n \\[\n = 0 - 1 + 2 - 3 = -2\n \\]"
    },
    {
      "type": "example",
      "id": "example-9.3",
      "number": "9.3",
      "title": "Writing in sigma notation",
      "problem": "Write each sum using sigma notation:\n\n1. $1 + 4 + 9 + 16 + \\cdots + 100$\n\n2. $3 + 6 + 9 + 12 + \\cdots + 60$\n\n3. $\\frac{1}{2} + \\frac{1}{4} + \\frac{1}{8} + \\cdots + \\frac{1}{256}$",
      "solution": "1. These are perfect squares $1^2, 2^2, \\ldots, 10^2$:\n \\[\n \\sum_{k=1}^{10} k^2\n \\]\n\n2. These are multiples of 3: $3(1), 3(2), \\ldots, 3(20)$:\n \\[\n \\sum_{k=1}^{20} 3k \\quad \\text{or} \\quad 3\\sum_{k=1}^{20} k\n \\]\n\n3. These are powers of $\\frac{1}{2}$: $\\frac{1}{2^1}, \\frac{1}{2^2}, \\ldots, \\frac{1}{2^8}$:\n \\[\n \\sum_{k=1}^{8} \\frac{1}{2^k} \\quad \\text{or} \\quad \\sum_{k=1}^{8} \\left(\\frac{1}{2}\\right)^k\n \\]"
    },
    {
      "type": "example",
      "id": "example-9.4",
      "number": "9.4",
      "title": "Writing more complex sums",
      "problem": "Write each sum using sigma notation:\n\n1. $2 - 4 + 6 - 8 + 10 - 12$\n\n2. $1 + \\frac{1}{2} + \\frac{1}{3} + \\frac{1}{4} + \\cdots + \\frac{1}{100}$\n\n3. $1 \\cdot 2 + 2 \\cdot 3 + 3 \\cdot 4 + \\cdots + 99 \\cdot 100$",
      "solution": "1. The terms are $2, 4, 6, \\ldots$ (even numbers) with alternating signs:\n \\[\n \\sum_{k=1}^{6} (-1)^{k+1} \\cdot 2k\n \\]\n\n2. These are reciprocals of positive integers:\n \\[\n \\sum_{k=1}^{100} \\frac{1}{k}\n \\]\n This is a partial sum of the **harmonic series**.\n\n3. Each term is $k(k+1)$:\n \\[\n \\sum_{k=1}^{99} k(k+1)\n \\]"
    },
    {
      "type": "heading",
      "level": 2,
      "text": "Properties of Summation"
    },
    {
      "type": "theorem",
      "id": "theorem-9.1",
      "number": "9.1",
      "title": "Summation Properties",
      "content": "For sequences $\\{a_k\\}$ and $\\{b_k\\}$ and constant $c$:\n\n1. **Constant multiple:** $\\displaystyle\\sum_{k=m}^{n} c \\cdot a_k = c \\sum_{k=m}^{n} a_k$\n\n2. **Sum rule:** $\\displaystyle\\sum_{k=m}^{n} (a_k + b_k) = \\sum_{k=m}^{n} a_k + \\sum_{k=m}^{n} b_k$\n\n3. **Difference rule:** $\\displaystyle\\sum_{k=m}^{n} (a_k - b_k) = \\sum_{k=m}^{n} a_k - \\sum_{k=m}^{n} b_k$\n\n4. **Sum of constant:** $\\displaystyle\\sum_{k=1}^{n} c = nc$",
      "label": "Theorem"
    },
    {
      "type": "paragraph",
      "text": "These properties let us break complex sums into simpler pieces, much \nlike factoring or distribution in algebra."
    },
    {
      "type": "example",
      "id": "example-9.5",
      "number": "9.5",
      "title": "Using summation properties",
      "problem": "Simplify $\\displaystyle\\sum_{k=1}^{100} (3k + 5)$.",
      "solution": "Using the properties:\n\\[\n \\sum_{k=1}^{100} (3k + 5) = \\sum_{k=1}^{100} 3k + \\sum_{k=1}^{100} 5 = 3\\sum_{k=1}^{100} k + 5(100)\n\\]\n\nWe know $\\displaystyle\\sum_{k=1}^{100} k = \\frac{100 \\cdot 101}{2} = 5050$\n\nTherefore:\n\\[\n 3(5050) + 500 = 15150 + 500 = 15650\n\\]"
    },
    {
      "type": "example",
      "id": "example-9.6",
      "number": "9.6",
      "title": "Decomposing a complex sum",
      "problem": "Evaluate $\\displaystyle\\sum_{k=1}^{50} (4k - 7)$.",
      "solution": "$$\n \\sum_{k=1}^{50} (4k - 7) &= 4\\sum_{k=1}^{50} k - \\sum_{k=1}^{50} 7 \\\\\n &= 4 \\cdot \\frac{50 \\cdot 51}{2} - 7 \\cdot 50 \\\\\n &= 4 \\cdot 1275 - 350 \\\\\n &= 5100 - 350 = 4750\n$$"
    },
    {
      "type": "example",
      "id": "example-9.7",
      "number": "9.7",
      "title": "Sum of a polynomial expression",
      "problem": "Evaluate $\\displaystyle\\sum_{k=1}^{10} (k^2 + 2k - 1)$.",
      "solution": "$$\n \\sum_{k=1}^{10} (k^2 + 2k - 1) &= \\sum_{k=1}^{10} k^2 + 2\\sum_{k=1}^{10} k - \\sum_{k=1}^{10} 1 \\\\\n &= \\frac{10 \\cdot 11 \\cdot 21}{6} + 2 \\cdot \\frac{10 \\cdot 11}{2} - 10 \\\\\n &= 385 + 110 - 10 \\\\\n &= 485\n$$"
    },
    {
      "type": "heading",
      "level": 2,
      "text": "Standard Summation Formulas"
    },
    {
      "type": "theorem",
      "id": "theorem-9.2",
      "number": "9.2",
      "title": "Common Summation Formulas",
      "content": "1. **Sum of first $n$ integers:**\n \\[\n \\sum_{k=1}^{n} k = 1 + 2 + 3 + \\cdots + n = \\frac{n(n+1)}{2}\n \\]\n\n2. **Sum of first $n$ squares:**\n \\[\n \\sum_{k=1}^{n} k^2 = 1^2 + 2^2 + \\cdots + n^2 = \\frac{n(n+1)(2n+1)}{6}\n \\]\n\n3. **Sum of first $n$ cubes:**\n \\[\n \\sum_{k=1}^{n} k^3 = 1^3 + 2^3 + \\cdots + n^3 = \\left[\\frac{n(n+1)}{2}\\right]^2\n \\]",
      "label": "Theorem"
    },
    {
      "type": "example",
      "id": "example-9.8",
      "number": "9.8",
      "title": "Applying the formulas",
      "problem": "Evaluate:\n\n1. $\\displaystyle\\sum_{k=1}^{20} k$\n\n2. $\\displaystyle\\sum_{k=1}^{10} k^2$\n\n3. $\\displaystyle\\sum_{k=1}^{5} k^3$",
      "solution": "1. $\\displaystyle\\sum_{k=1}^{20} k = \\frac{20 \\cdot 21}{2} = 210$\n\n2. $\\displaystyle\\sum_{k=1}^{10} k^2 = \\frac{10 \\cdot 11 \\cdot 21}{6} = \\frac{2310}{6} = 385$\n\n3. $\\displaystyle\\sum_{k=1}^{5} k^3 = \\left[\\frac{5 \\cdot 6}{2}\\right]^2 = 15^2 = 225$\n \n Check: $1 + 8 + 27 + 64 + 125 = 225$"
    },
    {
      "type": "example",
      "id": "example-9.9",
      "number": "9.9",
      "title": "Larger sums",
      "problem": "Evaluate:\n\n1. $1 + 2 + 3 + \\cdots + 1000$\n\n2. $1^2 + 2^2 + 3^2 + \\cdots + 50^2$\n\n3. $1^3 + 2^3 + 3^3 + \\cdots + 20^3$",
      "solution": "1. $\\displaystyle\\sum_{k=1}^{1000} k = \\frac{1000 \\cdot 1001}{2} = 500{,}500$\n\n2. $\\displaystyle\\sum_{k=1}^{50} k^2 = \\frac{50 \\cdot 51 \\cdot 101}{6} = \\frac{257{,}550}{6} = 42{,}925$\n\n3. $\\displaystyle\\sum_{k=1}^{20} k^3 = \\left[\\frac{20 \\cdot 21}{2}\\right]^2 = 210^2 = 44{,}100$"
    },
    {
      "type": "historical",
      "id": "historical-9.3",
      "number": null,
      "title": "Nicomachus's Theorem",
      "content": "The formula $\\sum k^3 = (\\sum k)^2$ is called Nicomachus's theorem, \nafter the Greek mathematician Nicomachus of Gerasa (c. 60–120 CE). It \nshows that the sum of the first $n$ cubes equals the square of the sum \nof the first $n$ integers—a beautiful and surprising result."
    },
    {
      "type": "example",
      "id": "example-9.10",
      "number": "9.10",
      "title": "Verifying Nicomachus's theorem",
      "problem": "Verify that $1^3 + 2^3 + 3^3 + 4^3 = (1 + 2 + 3 + 4)^2$.",
      "solution": "Left side: $1 + 8 + 27 + 64 = 100$\n\nRight side: $(10)^2 = 100$ \n\nThis remarkable identity holds for all $n$!"
    },
    {
      "type": "example",
      "id": "example-9.11",
      "number": "9.11",
      "title": "Complex sum",
      "problem": "Evaluate $\\displaystyle\\sum_{k=1}^{15} (2k^2 - 3k + 1)$.",
      "solution": "$$\n \\sum_{k=1}^{15} (2k^2 - 3k + 1) &= 2\\sum_{k=1}^{15} k^2 - 3\\sum_{k=1}^{15} k + \\sum_{k=1}^{15} 1 \\\\\n &= 2 \\cdot \\frac{15 \\cdot 16 \\cdot 31}{6} - 3 \\cdot \\frac{15 \\cdot 16}{2} + 15 \\\\\n &= 2 \\cdot \\frac{7440}{6} - 3 \\cdot 120 + 15 \\\\\n &= 2480 - 360 + 15 \\\\\n &= 2135\n$$"
    },
    {
      "type": "example",
      "id": "example-9.12",
      "number": "9.12",
      "title": "Sum of consecutive squares starting from $m$",
      "problem": "Find $\\displaystyle\\sum_{k=11}^{20} k^2$.",
      "solution": "\\[\n \\sum_{k=11}^{20} k^2 = \\sum_{k=1}^{20} k^2 - \\sum_{k=1}^{10} k^2\n\\]\n\\[\n = \\frac{20 \\cdot 21 \\cdot 41}{6} - \\frac{10 \\cdot 11 \\cdot 21}{6} = \\frac{17220}{6} - \\frac{2310}{6} = \\frac{14910}{6} = 2485\n\\]"
    },
    {
      "type": "heading",
      "level": 2,
      "text": "Telescoping Series"
    },
    {
      "type": "paragraph",
      "text": "A **telescoping series** is one where \nconsecutive terms cancel, leaving only a few terms remaining."
    },
    {
      "type": "example",
      "id": "example-9.13",
      "number": "9.13",
      "title": "Basic telescoping",
      "problem": "Evaluate $\\displaystyle\\sum_{k=1}^{100} \\left(\\frac{1}{k} - \\frac{1}{k+1}\\right)$.",
      "solution": "Write out several terms:\n\\[\n \\left(1 - \\frac{1}{2}\\right) + \\left(\\frac{1}{2} - \\frac{1}{3}\\right) + \\left(\\frac{1}{3} - \\frac{1}{4}\\right) + \\cdots + \\left(\\frac{1}{100} - \\frac{1}{101}\\right)\n\\]\n\nMost terms cancel! Only the first and last survive:\n\\[\n = 1 - \\frac{1}{101} = \\frac{100}{101}\n\\]"
    },
    {
      "type": "example",
      "id": "example-9.14",
      "number": "9.14",
      "title": "Partial fractions for telescoping",
      "problem": "Evaluate $\\displaystyle\\sum_{k=1}^{50} \\frac{1}{k(k+1)}$.",
      "solution": "Use partial fractions: $\\frac{1}{k(k+1)} = \\frac{1}{k} - \\frac{1}{k+1}$\n\nThen:\n\\[\n \\sum_{k=1}^{50} \\frac{1}{k(k+1)} = \\sum_{k=1}^{50} \\left(\\frac{1}{k} - \\frac{1}{k+1}\\right) = 1 - \\frac{1}{51} = \\frac{50}{51}\n\\]"
    },
    {
      "type": "example",
      "id": "example-9.15",
      "number": "9.15",
      "title": "Another telescoping sum",
      "problem": "Evaluate $\\displaystyle\\sum_{k=1}^{n} (k^2 - (k-1)^2)$.",
      "solution": "Expand and write out terms:\n\\[\n (1 - 0) + (4 - 1) + (9 - 4) + \\cdots + (n^2 - (n-1)^2)\n\\]\n\nThis telescopes to:\n\\[\n = n^2 - 0 = n^2\n\\]\n\nThis makes sense: $\\sum_{k=1}^{n} (k^2 - (k-1)^2) = \\sum_{k=1}^{n} (2k - 1) = n^2$ \n(sum of first $n$ odd integers)."
    },
    {
      "type": "example",
      "id": "example-9.16",
      "number": "9.16",
      "title": "Telescoping with squares",
      "problem": "Evaluate $\\displaystyle\\sum_{k=2}^{10} \\frac{1}{k^2 - 1}$.",
      "solution": "Factor: $k^2 - 1 = (k-1)(k+1)$\n\nPartial fractions: $\\frac{1}{(k-1)(k+1)} = \\frac{1}{2}\\left(\\frac{1}{k-1} - \\frac{1}{k+1}\\right)$\n\n$$\n \\sum_{k=2}^{10} \\frac{1}{k^2-1} &= \\frac{1}{2}\\sum_{k=2}^{10} \\left(\\frac{1}{k-1} - \\frac{1}{k+1}\\right) \\\\\n &= \\frac{1}{2}\\left[\\left(1 - \\frac{1}{3}\\right) + \\left(\\frac{1}{2} - \\frac{1}{4}\\right) + \\cdots + \\left(\\frac{1}{9} - \\frac{1}{11}\\right)\\right] \\\\\n &= \\frac{1}{2}\\left[1 + \\frac{1}{2} - \\frac{1}{10} - \\frac{1}{11}\\right] \\\\\n &= \\frac{1}{2} \\cdot \\frac{110 + 55 - 11 - 10}{110} = \\frac{144}{220} = \\frac{36}{55}\n$$"
    },
    {
      "type": "heading",
      "level": 2,
      "text": "Changing Indices"
    },
    {
      "type": "paragraph",
      "text": "Sometimes we need to adjust the index of summation. The key is that the \nactual sum doesn't change—only how we write it."
    },
    {
      "type": "example",
      "id": "example-9.17",
      "number": "9.17",
      "title": "Index shifting",
      "problem": "Rewrite $\\displaystyle\\sum_{k=0}^{4} (k+1)^2$ with index starting at 1.",
      "solution": "Let $j = k + 1$. When $k = 0$, $j = 1$. When $k = 4$, $j = 5$.\nThen $k = j - 1$, but $k + 1 = j$, so:\n\\[\n \\sum_{k=0}^{4} (k+1)^2 = \\sum_{j=1}^{5} j^2\n\\]\n\nVerify: Both equal $1 + 4 + 9 + 16 + 25 = 55$."
    },
    {
      "type": "example",
      "id": "example-9.18",
      "number": "9.18",
      "title": "Shifting to standard form",
      "problem": "Rewrite $\\displaystyle\\sum_{k=5}^{15} (2k - 3)$ as a sum starting from $k = 1$.",
      "solution": "Let $j = k - 4$. When $k = 5$, $j = 1$. When $k = 15$, $j = 11$.\nThen $k = j + 4$, so $2k - 3 = 2(j + 4) - 3 = 2j + 5$.\n\\[\n \\sum_{k=5}^{15} (2k - 3) = \\sum_{j=1}^{11} (2j + 5)\n\\]\n\nVerify: Original = $7 + 9 + 11 + \\cdots + 27 = 187$\n\nNew form = $\\sum_{j=1}^{11} (2j + 5) = 2 \\cdot \\frac{11 \\cdot 12}{2} + 55 = 132 + 55 = 187$"
    },
    {
      "type": "example",
      "id": "example-9.19",
      "number": "9.19",
      "title": "Splitting a sum",
      "problem": "Split $\\displaystyle\\sum_{k=1}^{100} k^2$ into two sums: one for $k = 1$ to 50 \nand one for $k = 51$ to 100.",
      "solution": "\\[\n \\sum_{k=1}^{100} k^2 = \\sum_{k=1}^{50} k^2 + \\sum_{k=51}^{100} k^2\n\\]\n\nWe can compute:\n\\[\n \\sum_{k=1}^{50} k^2 = \\frac{50 \\cdot 51 \\cdot 101}{6} = 42925\n\\]\n\\[\n \\sum_{k=1}^{100} k^2 = \\frac{100 \\cdot 101 \\cdot 201}{6} = 338350\n\\]\n\\[\n \\sum_{k=51}^{100} k^2 = 338350 - 42925 = 295425\n\\]"
    },
    {
      "type": "heading",
      "level": 2,
      "text": "The Fibonacci Sequence"
    },
    {
      "type": "definition",
      "id": "definition-9.2",
      "number": "9.2",
      "title": "Fibonacci Sequence",
      "content": "The **Fibonacci sequence** is defined \nrecursively by:\n\\[\n F_1 = 1, \\quad F_2 = 1, \\quad F_n = F_{n-1} + F_{n-2} \\text{ for } n \\geq 3\n\\]\nThe sequence is: $1, 1, 2, 3, 5, 8, 13, 21, 34, 55, 89, 144, \\ldots$"
    },
    {
      "type": "historical",
      "id": "historical-9.3",
      "number": null,
      "title": "Leonardo of Pisa (c. 1170--1250)",
      "content": "The Fibonacci sequence is named after Leonardo of Pisa, known as \nFibonacci. He introduced it in his book *Liber Abaci* (1202) \nwhile solving a problem about rabbit population growth. The sequence \nappears throughout nature: in the spiral of shells, the arrangement of \nleaves, and the pattern of sunflower seeds."
    },
    {
      "type": "example",
      "id": "example-9.20",
      "number": "9.20",
      "title": "Fibonacci terms",
      "problem": "Find $F_{10}$ and $F_{12}$.",
      "solution": "Continue the sequence:\n$$\n F_1 &= 1 & F_7 &= 13 \\\\\n F_2 &= 1 & F_8 &= 21 \\\\\n F_3 &= 2 & F_9 &= 34 \\\\\n F_4 &= 3 & F_{10} &= 55 \\\\\n F_5 &= 5 & F_{11} &= 89 \\\\\n F_6 &= 8 & F_{12} &= 144\n$$"
    },
    {
      "type": "example",
      "id": "example-9.21",
      "number": "9.21",
      "title": "Extended Fibonacci",
      "problem": "Find $F_{15}$.",
      "solution": "Continuing from $F_{12} = 144$:\n$$\n F_{13} &= F_{12} + F_{11} = 144 + 89 = 233 \\\\\n F_{14} &= F_{13} + F_{12} = 233 + 144 = 377 \\\\\n F_{15} &= F_{14} + F_{13} = 377 + 233 = 610\n$$"
    },
    {
      "type": "theorem",
      "id": "theorem-9.3",
      "number": "9.3",
      "title": "Fibonacci Sum Property",
      "content": "The sum of the first $n$ Fibonacci numbers is:\n\\[\n \\sum_{k=1}^{n} F_k = F_{n+2} - 1\n\\]",
      "label": "Theorem"
    },
    {
      "type": "example",
      "id": "example-9.22",
      "number": "9.22",
      "title": "Sum of Fibonacci numbers",
      "problem": "Find $F_1 + F_2 + F_3 + F_4 + F_5 + F_6$.",
      "solution": "Using the formula: $\\sum_{k=1}^{6} F_k = F_8 - 1 = 21 - 1 = 20$\n\nCheck: $1 + 1 + 2 + 3 + 5 + 8 = 20$"
    },
    {
      "type": "example",
      "id": "example-9.23",
      "number": "9.23",
      "title": "Verifying the Fibonacci sum formula",
      "problem": "Verify that $F_1 + F_2 + \\cdots + F_{10} = F_{12} - 1$.",
      "solution": "Left side: $1 + 1 + 2 + 3 + 5 + 8 + 13 + 21 + 34 + 55 = 143$\n\nRight side: $F_{12} - 1 = 144 - 1 = 143$"
    },
    {
      "type": "definition",
      "id": "definition-9.3",
      "number": "9.3",
      "title": "Golden Ratio",
      "content": "The **golden ratio** is:\n\\[\n \\phi = \\frac{1 + \\sqrt{5}}{2} \\approx 1.618033988749...\n\\]\nThe ratio $\\frac{F_{n+1}}{F_n}$ approaches $\\phi$ as $n \\to \\infty$."
    },
    {
      "type": "example",
      "id": "example-9.24",
      "number": "9.24",
      "title": "Approaching the golden ratio",
      "problem": "Compute $\\frac{F_{n+1}}{F_n}$ for several values of $n$.",
      "solution": "$$\n \\frac{F_2}{F_1} &= \\frac{1}{1} = 1.000 \\\\\n \\frac{F_3}{F_2} &= \\frac{2}{1} = 2.000 \\\\\n \\frac{F_5}{F_4} &= \\frac{5}{3} = 1.667 \\\\\n \\frac{F_7}{F_6} &= \\frac{13}{8} = 1.625 \\\\\n \\frac{F_{10}}{F_9} &= \\frac{55}{34} \\approx 1.618 \\\\\n \\frac{F_{12}}{F_{11}} &= \\frac{144}{89} \\approx 1.618\n$$\n\nThe ratios oscillate around $\\phi \\approx 1.618$ and converge to it."
    },
    {
      "type": "theorem",
      "id": "theorem-9.4",
      "number": "9.4",
      "title": "Binet's Formula",
      "content": "The $n$th Fibonacci number can be computed directly:\n\\[\n F_n = \\frac{\\phi^n - \\psi^n}{\\sqrt{5}}\n\\]\nwhere $\\phi = \\frac{1 + \\sqrt{5}}{2}$ and $\\psi = \\frac{1 - \\sqrt{5}}{2}$.",
      "label": "Theorem"
    },
    {
      "type": "paragraph",
      "text": "This remarkable formula gives an exact integer result despite containing \nirrational numbers!"
    },
    {
      "type": "heading",
      "level": 2,
      "text": "Other Special Sequences"
    },
    {
      "type": "definition",
      "id": "definition-9.4",
      "number": "9.4",
      "title": "Triangular Numbers",
      "content": "The **triangular numbers** are:\n\\[\n T_n = 1 + 2 + 3 + \\cdots + n = \\frac{n(n+1)}{2}\n\\]\nThe sequence is: $1, 3, 6, 10, 15, 21, 28, 36, 45, 55, \\ldots$"
    },
    {
      "type": "example",
      "id": "example-9.25",
      "number": "9.25",
      "title": "Triangular numbers in nature",
      "problem": "153 is a triangular number. Verify this and find which triangular \nnumber it is.",
      "solution": "We need $\\frac{n(n+1)}{2} = 153$, so $n(n+1) = 306$.\n\nSolving: $n^2 + n - 306 = 0$\n\nUsing the quadratic formula: $n = \\frac{-1 + \\sqrt{1 + 1224}}{2} = \\frac{-1 + 35}{2} = 17$\n\nSo $153 = T_{17}$. The number 153 from John 21:11 (the fish caught) \nis the 17th triangular number."
    },
    {
      "type": "definition",
      "id": "definition-9.5",
      "number": "9.5",
      "title": "Square Numbers",
      "content": "The **square numbers** are:\n\\[\n S_n = n^2 = 1, 4, 9, 16, 25, 36, 49, 64, 81, 100, \\ldots\n\\]"
    },
    {
      "type": "theorem",
      "id": "theorem-9.5",
      "number": "9.5",
      "title": "Triangular-Square Relationship",
      "content": "The sum of two consecutive triangular numbers is a square number:\n\\[\n T_{n-1} + T_n = n^2\n\\]",
      "label": "Theorem"
    },
    {
      "type": "example",
      "id": "example-9.26",
      "number": "9.26",
      "title": "Verifying the relationship",
      "problem": "Verify that $T_4 + T_5 = 5^2$.",
      "solution": "$T_4 = 10$ and $T_5 = 15$\n\n$T_4 + T_5 = 10 + 15 = 25 = 5^2$"
    },
    {
      "type": "definition",
      "id": "definition-9.6",
      "number": "9.6",
      "title": "Pentagonal Numbers",
      "content": "The **pentagonal numbers** are:\n\\[\n P_n = \\frac{n(3n-1)}{2}\n\\]\nThe sequence is: $1, 5, 12, 22, 35, 51, 70, 92, \\ldots$"
    },
    {
      "type": "example",
      "id": "example-9.27",
      "number": "9.27",
      "title": "Computing pentagonal numbers",
      "problem": "Find $P_5$ and $P_6$.",
      "solution": "$P_5 = \\frac{5(15-1)}{2} = \\frac{70}{2} = 35$\n\n$P_6 = \\frac{6(18-1)}{2} = \\frac{102}{2} = 51$"
    },
    {
      "type": "heading",
      "level": 2,
      "text": "Introduction to Series Convergence"
    },
    {
      "type": "paragraph",
      "text": "We've seen that geometric series with $|r| < 1$ converge to finite \nsums. Let's explore convergence more generally."
    },
    {
      "type": "definition",
      "id": "definition-9.7",
      "number": "9.7",
      "title": "Partial Sums and Convergence",
      "content": "For a series $\\sum_{k=1}^{\\infty} a_k$, the **partial sums** are:\n\\[\n S_n = a_1 + a_2 + \\cdots + a_n\n\\]\nThe series **converges** if $\\lim_{n \\to \\infty} S_n$ exists and \nis finite. Otherwise, it **diverges**."
    },
    {
      "type": "theorem",
      "id": "theorem-9.6",
      "number": "9.6",
      "title": "Necessary Condition for Convergence",
      "content": "If $\\sum_{k=1}^{\\infty} a_k$ converges, then $\\lim_{n \\to \\infty} a_n = 0$.",
      "label": "Theorem"
    },
    {
      "type": "warning",
      "id": "warning-9.3",
      "number": null,
      "title": "Converse is False!",
      "content": "The condition $a_n \\to 0$ is necessary but not sufficient for \nconvergence. The harmonic series $\\sum \\frac{1}{n}$ has $\\frac{1}{n} \\to 0$ \nbut diverges!"
    },
    {
      "type": "example",
      "id": "example-9.28",
      "number": "9.28",
      "title": "Testing for divergence",
      "problem": "Determine whether each series could possibly converge.\n\n1. $\\sum_{n=1}^{\\infty} \\frac{n}{n+1}$\n\n2. $\\sum_{n=1}^{\\infty} \\frac{1}{n^2}$\n\n3. $\\sum_{n=1}^{\\infty} (-1)^n$",
      "solution": "1. $\\lim_{n \\to \\infty} \\frac{n}{n+1} = 1 \\neq 0$. The series **diverges**.\n\n2. $\\lim_{n \\to \\infty} \\frac{1}{n^2} = 0$. The series **might converge** \n (it does—this is the Basel problem, with sum $\\frac{\\pi^2}{6}$).\n\n3. $\\lim_{n \\to \\infty} (-1)^n$ does not exist. The series **diverges**."
    },
    {
      "type": "historical",
      "id": "historical-9.3",
      "number": null,
      "title": "The Harmonic Series",
      "content": "The harmonic series $1 + \\frac{1}{2} + \\frac{1}{3} + \\frac{1}{4} + \\cdots$ \nwas proven to diverge by Nicole Oresme in the 14th century. His proof: \nGroup terms as $(1) + (\\frac{1}{2}) + (\\frac{1}{3} + \\frac{1}{4}) + \n(\\frac{1}{5} + \\frac{1}{6} + \\frac{1}{7} + \\frac{1}{8}) + \\cdots$. Each \ngroup (after the first) sums to at least $\\frac{1}{2}$, so the total \nexceeds any bound."
    },
    {
      "type": "example",
      "id": "example-9.29",
      "number": "9.29",
      "title": "The harmonic series diverges",
      "problem": "Show that the partial sums of $\\sum \\frac{1}{n}$ grow without bound.",
      "solution": "Group the terms:\n$$\n S_1 &= 1 \\\\\n S_2 &= 1 + \\frac{1}{2} = \\frac{3}{2} \\\\\n S_4 &> 1 + \\frac{1}{2} + \\frac{1}{4} + \\frac{1}{4} = 2 \\\\\n S_8 &> 1 + \\frac{1}{2} + \\frac{1}{2} + \\frac{1}{2} = \\frac{5}{2} \\\\\n S_{16} &> 3 \\\\\n S_{2^n} &> 1 + \\frac{n}{2}\n$$\n\nAs $n \\to \\infty$, the partial sums grow without bound, so the series \ndiverges—despite the terms approaching zero!"
    },
    {
      "type": "heading",
      "level": 2,
      "text": "Applications of Sigma Notation"
    },
    {
      "type": "example",
      "id": "example-9.30",
      "number": "9.30",
      "title": "Average calculation",
      "problem": "A student's quiz scores are 85, 92, 78, 95, 88, and 91. Express the \nmean using sigma notation and calculate it.",
      "solution": "Let $x_1 = 85, x_2 = 92, x_3 = 78, x_4 = 95, x_5 = 88, x_6 = 91$.\n\nMean = $\\displaystyle\\frac{1}{6}\\sum_{k=1}^{6} x_k = \\frac{85 + 92 + 78 + 95 + 88 + 91}{6} = \\frac{529}{6} \\approx 88.17$"
    },
    {
      "type": "example",
      "id": "example-9.31",
      "number": "9.31",
      "title": "Variance in statistics",
      "problem": "The variance of a dataset $\\{x_1, x_2, \\ldots, x_n\\}$ with mean $\\bar{x}$ is:\n\\[\n \\sigma^2 = \\frac{1}{n}\\sum_{k=1}^{n} (x_k - \\bar{x})^2\n\\]\nFind the variance for the scores 2, 4, 6, 8, 10.",
      "solution": "Mean: $\\bar{x} = \\frac{2 + 4 + 6 + 8 + 10}{5} = 6$\n\n$$\n \\sigma^2 &= \\frac{1}{5}\\sum_{k=1}^{5} (x_k - 6)^2 \\\\\n &= \\frac{1}{5}[(2-6)^2 + (4-6)^2 + (6-6)^2 + (8-6)^2 + (10-6)^2] \\\\\n &= \\frac{1}{5}[16 + 4 + 0 + 4 + 16] \\\\\n &= \\frac{40}{5} = 8\n$$\n\nStandard deviation: $\\sigma = \\sqrt{8} \\approx 2.83$"
    },
    {
      "type": "example",
      "id": "example-9.32",
      "number": "9.32",
      "title": "Payment schedule",
      "problem": "A loan is repaid with monthly payments that decrease by \\$10 each month. \nThe first payment is \\$500. Express the total paid over 12 months using \nsigma notation.",
      "solution": "The payments are: $500, 490, 480, \\ldots$ (arithmetic with $d = -10$).\n\nPayment in month $k$: $a_k = 500 - 10(k-1) = 510 - 10k$\n\nTotal paid:\n\\[\n \\sum_{k=1}^{12} (510 - 10k) = 510(12) - 10\\sum_{k=1}^{12} k = 6120 - 10 \\cdot \\frac{12 \\cdot 13}{2} = 6120 - 780 = \\$5340\n\\]"
    },
    {
      "type": "example",
      "id": "example-9.33",
      "number": "9.33",
      "title": "Area under a curve (preview of calculus)",
      "problem": "Approximate the area under $y = x^2$ from $x = 0$ to $x = 4$ using \n4 rectangles of equal width.",
      "solution": "Width of each rectangle: $\\Delta x = 1$\n\nHeights (using right endpoints): $f(1) = 1$, $f(2) = 4$, $f(3) = 9$, $f(4) = 16$\n\nArea $\\approx \\sum_{k=1}^{4} f(k) \\cdot 1 = 1 + 4 + 9 + 16 = 30$\n\n(The actual area is $\\frac{64}{3} \\approx 21.33$—the approximation is \nan overestimate because we used right endpoints.)"
    },
    {
      "type": "example",
      "id": "example-9.34",
      "number": "9.34",
      "title": "Riemann sums",
      "problem": "Approximate the area under $y = x^2$ from $x = 0$ to $x = 2$ using $n$ \nrectangles with right endpoints.",
      "solution": "Width: $\\Delta x = \\frac{2}{n}$\n\nRight endpoints: $x_k = \\frac{2k}{n}$ for $k = 1, 2, \\ldots, n$\n\nHeights: $f(x_k) = \\left(\\frac{2k}{n}\\right)^2 = \\frac{4k^2}{n^2}$\n\nArea $\\approx \\sum_{k=1}^{n} \\frac{4k^2}{n^2} \\cdot \\frac{2}{n} = \\frac{8}{n^3}\\sum_{k=1}^{n} k^2 = \\frac{8}{n^3} \\cdot \\frac{n(n+1)(2n+1)}{6}$\n\n$= \\frac{8(n+1)(2n+1)}{6n^2} = \\frac{4(n+1)(2n+1)}{3n^2}$\n\nAs $n \\to \\infty$: $\\lim_{n \\to \\infty} \\frac{4(n+1)(2n+1)}{3n^2} = \\frac{4 \\cdot 2}{3} = \\frac{8}{3}$\n\nThe exact area is $\\frac{8}{3}$."
    }
  ],
  "marginNotes": [
    {
      "type": "scripture",
      "reference": "Revelation 7:9",
      "text": "After this I looked, and there before \nme was a great multitude that no one could count."
    },
    {
      "type": "scripture",
      "reference": "1 Chronicles 21:1--2",
      "text": "Satan rose up against Israel and \nincited David to take a census of Israel. So David said to Joab and the \ncommanders of the troops, \"Go and count the Israelites.\""
    },
    {
      "type": "scripture",
      "reference": "Romans 12:4--5",
      "text": "For just as each of us has one body \nwith many members, and these members do not all have the same function, \nso in Christ we, though many, form one body."
    },
    {
      "type": "scripture",
      "reference": "Psalm 139:17--18",
      "text": "How precious to me are your thoughts, \nGod! How vast is the sum of them! Were I to count them, they would \noutnumber the grains of sand."
    },
    {
      "type": "scripture",
      "reference": "Genesis 1:11--12",
      "text": "Then God said, \"Let the land produce \nvegetation: seed-bearing plants and trees.\" And it was so."
    },
    {
      "type": "scripture",
      "reference": "John 21:11",
      "text": "So Simon Peter climbed back into the boat \nand dragged the net ashore. It was full of large fish, 153, but even \nwith so many the net was not torn."
    }
  ]
}