{
  "id": "pre-algebra-ch07-sec01",
  "title": "Variables and Algebraic Expressions",
  "chapter": 7,
  "section": 1,
  "book": "pre-algebra",
  "epigraph": {
    "text": "The heavens declare the glory of God; the skies \nproclaim the work of his hands.",
    "reference": "Psalm 19:1"
  },
  "content": [
    {
      "type": "paragraph",
      "text": "When mathematicians write $x + 5$, they are not being mysterious. \nThe letter $x$ simply represents a number we don't know yet—or a \nnumber that could take many different values. This simple idea \ntransforms arithmetic into algebra."
    },
    {
      "type": "heading",
      "level": 2,
      "text": "What Are Variables?"
    },
    {
      "type": "definition",
      "id": "definition-7.1",
      "number": "7.1",
      "title": "Variable",
      "content": "A **variable** is a letter or symbol that represents \na number. Common variable letters include $x$, $y$, $z$, $a$, $b$, $c$, $n$, and $t$."
    },
    {
      "type": "paragraph",
      "text": "Variables allow us to:"
    },
    {
      "type": "list",
      "ordered": false,
      "items": [
        "Represent unknown values",
        "Write general rules that work for many numbers",
        "Create formulas that describe relationships"
      ]
    },
    {
      "type": "example",
      "id": "example-7.1",
      "number": "7.1",
      "title": "Variables in context",
      "problem": "Identify the variable and explain what it represents:\n\n1. The perimeter of a square is $P = 4s$\n\n2. A taxi charges $5 + 2m$ dollars for a ride of $m$ miles\n\n3. Your age in $t$ years will be $14 + t$",
      "solution": "1. Variable $s$ represents the side length; $P$ represents perimeter\n\n2. Variable $m$ represents the number of miles traveled\n\n3. Variable $t$ represents the number of years from now"
    },
    {
      "type": "heading",
      "level": 2,
      "text": "Algebraic Expressions"
    },
    {
      "type": "paragraph",
      "text": "Ren\\'{e Descartes}{Each problem that I solved became a rule, \nwhich served afterwards to solve other problems.}"
    },
    {
      "type": "definition",
      "id": "definition-7.2",
      "number": "7.2",
      "title": "Algebraic Expression",
      "content": "An **algebraic expression** is a \nmathematical phrase that contains numbers, variables, and operation \nsymbols ($+$, $-$, $\\times$, $\\div$)."
    },
    {
      "type": "paragraph",
      "text": "Examples of algebraic expressions:"
    },
    {
      "type": "list",
      "ordered": false,
      "items": [
        "$3x + 7$",
        "$2a - 5b$",
        "$\\displaystyle \\frac{n + 1}{4}$",
        "$x^2 + 2x + 1$"
      ]
    },
    {
      "type": "paragraph",
      "text": "Note: An algebraic expression does *not* contain an equals sign. \nWhen an equals sign is present, we have an *equation*, not just \nan expression."
    },
    {
      "type": "heading",
      "level": 2,
      "text": "Parts of an Expression"
    },
    {
      "type": "definition",
      "id": "definition-7.3",
      "number": "7.3",
      "title": "Terms, Coefficients, and Constants",
      "content": "- A **term** is a part of an expression separated \n by addition or subtraction signs\n\n- A **coefficient** is the numerical factor \n of a term containing a variable\n\n- A **constant** is a term with no variable"
    },
    {
      "type": "example",
      "id": "example-7.2",
      "number": "7.2",
      "title": "Identifying parts",
      "problem": "For the expression $5x^2 - 3x + 7$, identify:\n\n1. The terms\n\n2. The coefficients\n\n3. The constant",
      "solution": "1. Terms: $5x^2$, $-3x$, and $7$\n\n2. Coefficients: $5$ (for $x^2$) and $-3$ (for $x$)\n\n3. Constant: $7$"
    },
    {
      "type": "heading",
      "level": 2,
      "text": "Multiplication in Algebra"
    },
    {
      "type": "paragraph",
      "text": "In algebra, we usually omit the multiplication sign to avoid confusion \nwith the variable $x$. These all mean the same thing:"
    },
    {
      "type": "method",
      "id": "method-7.1",
      "number": null,
      "title": "Writing Multiplication in Algebra",
      "content": "- Write the coefficient (number) first: $3x$ not $x3$\n\n- Write variables in alphabetical order: $2ab$ not $2ba$\n\n- $1 \\cdot x$ is written simply as $x$ (coefficient of 1 is implied)\n\n- $(-1) \\cdot x$ is written as $-x$"
    },
    {
      "type": "example",
      "id": "example-7.3",
      "number": "7.3",
      "title": "Rewriting expressions",
      "problem": "Rewrite using standard algebraic notation:\n\n1. $4 \\times y$\n\n2. $n \\times 7$\n\n3. $1 \\times a + b \\times (-3)$\n\n4. $x \\times x \\times x$",
      "solution": "1. $4y$\n\n2. $7n$\n\n3. $a - 3b$\n\n4. $x^3$"
    },
    {
      "type": "heading",
      "level": 2,
      "text": "Exponents with Variables"
    },
    {
      "type": "paragraph",
      "text": "When a variable is multiplied by itself, we use exponents:"
    },
    {
      "type": "paragraph",
      "text": "$$x \\cdot x &= x^2 \\quad \\text{(``$x$ squared'')} \\\\\nx \\cdot x \\cdot x &= x^3 \\quad \\text{(``$x$ cubed'')} \\\\\nx \\cdot x \\cdot x \\cdot x &= x^4 \\quad \\text{(``$x$ to the fourth'')}$$"
    },
    {
      "type": "example",
      "id": "example-7.4",
      "number": "7.4",
      "title": "Working with exponents",
      "problem": "Write in exponential form:\n\n1. $y \\cdot y \\cdot y \\cdot y \\cdot y$\n\n2. $3 \\cdot a \\cdot a \\cdot b \\cdot b \\cdot b$",
      "solution": "1. $y^5$\n\n2. $3a^2b^3$"
    },
    {
      "type": "historical",
      "id": "historical-7.1",
      "number": null,
      "title": "The Origin of $x$",
      "content": "Why do we use $x$ for the unknown? Some historians believe it came from \nthe Arabic word *shay* (thing), which was written *xay* in \nmedieval Spanish. Ren\\'{e} Descartes popularized using letters from the \nend of the alphabet ($x$, $y$, $z$) for unknowns and letters from the \nbeginning ($a$, $b$, $c$) for known quantities in his 1637 work \n*La G\\'{e*om\\'{e}trie}."
    }
  ],
  "marginNotes": [
    {
      "type": "scripture",
      "reference": "1 Corinthians 13:12",
      "text": "For now we see only a reflection as \nin a mirror; then we shall see face to face."
    },
    {
      "type": "scripture",
      "reference": "1 Corinthians 12:12",
      "text": "Just as a body, though one, has \nmany parts, but all its many parts form one body, so it is with Christ."
    },
    {
      "type": "scripture",
      "reference": "Genesis 22:17",
      "text": "I will surely bless you and make your \ndescendants as numerous as the stars in the sky."
    },
    {
      "type": "quote",
      "author": "Carl Friedrich Gauss",
      "text": "It is not knowledge, but the act of \nlearning, that grants the greatest enjoyment."
    }
  ]
}